milicar_1218_16/3/d_flipflop.vhdl
library ieee;
use IEEE.std_logic_1164.all;
use ieee.numeric_std.all;

entity d_flipflop is
    port(
        clk : in std_logic;
        d: in std_logic;
        reset : in std_logic;
        q : out std_logic

    );
    end d_flipflop;

    architecture d_flipflop_arch of d_flipflop is
    begin
    process(clk,reset)
     begin
    if(reset='1') then 
    q <= '0';
    elsif(rising_edge(clk)) then
     q <= d;
     end if;

    end process;

     end d_flipflop_arch;

milicar_1218_16/3/d_flipflop_testbench.vhdl
library ieee;
use ieee.std_logic_1164.all;
use ieee.numeric_std.all;

entity d_testbench is 
end d_testbench;

architecture d_arch of d_testbench is
component d_flipflop is
    port 
    (
        clk : in std_logic;
        d : in std_logic;
        reset : in std_logic;
        q : out std_logic
    );
end component;
signal clk_test : std_logic;
signal d_test : std_logic;
signal reset_test : std_logic;
signal q_test : std_logic;
signal i:integer:=0;
constant num_of_clks : integer:= 10;

begin
DUT: d_flipflop port map(clk_test,d_test, reset_test,q_test);

process
begin 
clk_test <= '1';
wait for 0.5 ns;
clk_test <= '0';
wait for 0.5 ns;

if(i=num_of_clks) then 
    wait;
else 
    i <= i+1;
end if;
end process;

process
begin 
d_test <= '0';
wait for 1 ns;
--assert((q_test='0' and reset_test='0') or (q_test='0' and reset_test='1')) report "Fail" severity error;

d_test <= '1';
wait for 1 ns;
--assert((q_test='1' and reset_test='0') or (q_test='0' and reset_test='1')) report "Fail" severity error;

d_test <= '1';
wait for 1 ns;
--assert((q_test='1' and reset_test='0') or (q_test='0' and reset_test='1')) report "Fail" severity error;

d_test <= '0';
wait for 1 ns;
--assert((q_test='0' and reset_test='0') or (q_test='0' and reset_test='1')) report "Fail" severity error;

wait;
end process;

reset_test <= '1' , '0' after 2 ns;

end d_arch;

milicar_1218_16/3/d_flipflop/moj_Test_vcd.vcd
$date
  Mon Sep 11 17:39:16 2023
$end
$version
  GHDL v0
$end
$timescale
  1 fs
$end
$scope module standard $end
$upscope $end
$scope module std_logic_1164 $end
$upscope $end
$scope module numeric_std $end
$upscope $end
$scope module d_testbench $end
$var reg 1 ! clk_test $end
$var reg 1 " d_test $end
$var reg 1 # reset_test $end
$var reg 1 $ q_test $end
$var integer 32 % i $end
$scope module dut $end
$var reg 1 & clk $end
$var reg 1 ' d $end
$var reg 1 ( reset $end
$var reg 1 ) q $end
$upscope $end
$upscope $end
$enddefinitions $end
#0
1!
0"
1#
0$
b0 %
1&
0'
1(
0)
#500000
0!
0&
#1000000
1!
1"
b1 %
1&
1'
#1500000
0!
0&
#2000000
1!
0#
1$
b10 %
1&
0(
1)
#2500000
0!
0&
#3000000
1!
0"
0$
b11 %
1&
0'
0)
#3500000
0!
0&
#4000000
1!
b100 %
1&
#4500000
0!
0&
#5000000
1!
b101 %
1&
#5500000
0!
0&
#6000000
1!
b110 %
1&
#6500000
0!
0&
#7000000
1!
b111 %
1&
#7500000
0!
0&
#8000000
1!
b1000 %
1&
#8500000
0!
0&
#9000000
1!
b1001 %
1&
#9500000
0!
0&
#10000000
1!
b1010 %
1&
