nikolab1213_20/vjezba3/JK_flip_flop.vhdl
library ieee;
use ieee.std_logic_1164.all;

entity JK_flip_flop is 
port(
    J, K, clk : in std_logic;
    Q, nQ : out std_logic
);
end JK_flip_flop;

architecture JK_flip_flop_beh of JK_flip_flop is
signal outp : std_logic := '0';
begin
process(clk)
begin
if(clk = '1' and clk'event) then
    if (J = '1' and K = '1') then
        outp <= not(outp);
    elsif (J = '1' and K = '0') then
        outp <= '1';
    elsif (J = '0' and K = '1') then
        outp <= '0';
    elsif (J = '0' and K = '0') then
        outp <= outp;
    end if;
end if;
Q <= outp;
nQ <= not(outp);
end process;
end JK_flip_flop_beh;

nikolab1213_20/vjezba3/JK_flip_flop_tb.vhdl
library ieee;
use ieee.std_logic_1164.all;

entity JK_testbench is
end JK_testbench;

architecture JK_tb of JK_testbench is
component JK_flip_flop is
port(
    J, K, clk : in std_logic;
    Q, nQ : out std_logic
);
end component;

signal J_in, K_in, clk_in, Q_out, nQ_out: std_logic;

begin
DUT: JK_flip_flop port map(
    J => J_in, 
    K => K_in,
    clk => clk_in,
    Q => Q_out, 
    nQ => nQ_out);
process
begin

J_in <= '0';
K_in <= '0';
clk_in <= '1';
wait for 1 ns;
clk_in <= '0';
wait for 1 ns;
assert(Q_out='0') report "Fail J = 0, K = 0" severity error;
assert(nQ_out='1') report "Fail J = 0, K = 0" severity error;
wait for 1 ns;

J_in <= '1';
K_in <= '0';
clk_in <= '1';
wait for 1 ns;
clk_in <= '0';
wait for 1 ns;
assert(Q_out='1') report "Fail J = 1, K = 0" severity error;
assert(nQ_out='0') report "Fail J = 1, K = 0" severity error;
wait for 1 ns;

J_in <= '0';
K_in <= '1';
clk_in <= '1';
wait for 1 ns;
clk_in <= '0';
wait for 1 ns;
assert(Q_out='0') report "Fail J = 0, K = 1" severity error;
assert(nQ_out='1') report "Fail J = 0, K = 1" severity error;
wait for 1 ns;

J_in <= '1';
K_in <= '1';
clk_in <= '1';
wait for 1 ns;
clk_in <= '0';
wait for 1 ns;
assert(Q_out='1') report "Fail J = 1, K = 1" severity error;
assert(nQ_out='0') report "Fail J = 1, K = 1" severity error;
wait for 1 ns;

J_in <= '1';
K_in <= '1';
wait for 1 ns;
assert(Q_out='1') report "Clock error" severity error;
assert(nQ_out='0') report "Clock error" severity error;

J_in <= '0';
K_in <= '0';
clk_in <= '0';
assert false report "Test finished" severity note;
wait;


end process;
end JK_tb;

nikolab1213_20/vjezba3/JK_flip_flop.vcd
$date
  Sat Apr 15 16:20:29 2023
$end
$version
  GHDL v0
$end
$timescale
  1 fs
$end
$scope module standard $end
$upscope $end
$scope module std_logic_1164 $end
$upscope $end
$scope module jk_testbench $end
$var reg 1 ! j_in $end
$var reg 1 " k_in $end
$var reg 1 # clk_in $end
$var reg 1 $ q_out $end
$var reg 1 % nq_out $end
$scope module dut $end
$var reg 1 & j $end
$var reg 1 ' k $end
$var reg 1 ( clk $end
$var reg 1 ) q $end
$var reg 1 * nq $end
$var reg 1 + outp $end
$upscope $end
$upscope $end
$enddefinitions $end
#0
0!
0"
1#
0$
1%
0&
0'
1(
0)
1*
0+
#1000000
0#
0(
#2000000
#3000000
1!
1#
1&
1(
1+
#4000000
0#
1$
0%
0(
1)
0*
#5000000
#6000000
0!
1"
1#
0&
1'
1(
0+
#7000000
0#
0$
1%
0(
0)
1*
#8000000
#9000000
1!
1#
1&
1(
1+
#10000000
0#
1$
0%
0(
1)
0*
#11000000
#12000000
#13000000
0!
0"
0&
0'
