nikolab1213_20/vjezba3/T_flip_flop.vhdl
library ieee;
use ieee.std_logic_1164.all;

entity T_flip_flop is
port(
    T, clk : in std_logic;
    Q, nQ : out std_logic
);
end T_flip_flop;

architecture T_flip_flop_beh of T_flip_flop is
signal outp : std_logic := '0';
begin
process(clk)
begin
if (clk = '1' and clk'event) then
    if (T = '1') then
        outp <= not(outp);
    end if;
end if;
Q <= outp;
nQ <= not(outp);
end process;
end T_flip_flop_beh;

nikolab1213_20/vjezba3/T_flip_flop_tb.vhdl
library ieee;
use ieee.std_logic_1164.all;

entity T_testbench is
end T_testbench;

architecture T_tb of T_testbench is
component T_flip_flop is
port(
    T, clk : in std_logic;
    Q, nQ : out std_logic
);
end component;

signal T_in, clk_in, Q_out, nQ_out: std_logic;

begin
DUT: T_flip_flop port map(
    T => T_in, 
    clk => clk_in,
    Q => Q_out, 
    nQ => nQ_out);
process
begin

T_in <= '0';
clk_in <= '0';
wait for 1 ns;
clk_in <= '0';
wait for 1 ns;
assert(Q_out='0') report "Fail T = 0, clk = 0" severity error;
assert(nQ_out='1') report "Fail T = 0, clk = 0" severity error;
wait for 1 ns;

T_in <= '1';
clk_in <= '0';
wait for 1 ns;
clk_in <= '0';
wait for 1 ns;
assert(Q_out='0') report "Fail T = 1, clk = 0" severity error;
assert(nQ_out='1') report "Fail T = 1, clk = 0" severity error;
wait for 1 ns;

T_in <= '1';
clk_in <= '1';
wait for 1 ns;
clk_in <= '0';
wait for 1 ns;
assert(Q_out='1') report "Fail T = 1, clk = 1" severity error;
assert(nQ_out='0') report "Fail T = 1, clk = 1" severity error;
wait for 1 ns;

T_in <= '0';
clk_in <= '1';
wait for 1 ns;
clk_in <= '0';
wait for 1 ns;
assert(Q_out='1') report "Fail T = 0, clk = 1" severity error;
assert(nQ_out='0') report "Fail T = 0, clk = 1" severity error;
wait for 1 ns;

T_in <= '1';
clk_in <= '1';
wait for 1 ns;
clk_in <= '0';
wait for 1 ns;
assert(Q_out='0') report "Fail T = 1, clk = 1" severity error;
assert(nQ_out='1') report "Fail T = 1, clk = 1" severity error;
wait for 1 ns;

T_in <= '0';
clk_in <= '0';
assert false report "Test finished" severity note;
wait;

end process;
end T_tb;

nikolab1213_20/vjezba3/T_flip_flop.vcd
$date
  Sat Apr 15 16:58:51 2023
$end
$version
  GHDL v0
$end
$timescale
  1 fs
$end
$scope module standard $end
$upscope $end
$scope module std_logic_1164 $end
$upscope $end
$scope module t_testbench $end
$var reg 1 ! t_in $end
$var reg 1 " clk_in $end
$var reg 1 # q_out $end
$var reg 1 $ nq_out $end
$scope module dut $end
$var reg 1 % t $end
$var reg 1 & clk $end
$var reg 1 ' q $end
$var reg 1 ( nq $end
$var reg 1 ) outp $end
$upscope $end
$upscope $end
$enddefinitions $end
#0
0!
0"
0#
1$
0%
0&
0'
1(
0)
#1000000
#2000000
#3000000
1!
1%
#4000000
#5000000
#6000000
1"
1&
1)
#7000000
0"
1#
0$
0&
1'
0(
#8000000
#9000000
0!
1"
0%
1&
#10000000
0"
0&
#11000000
#12000000
1!
1"
1%
1&
0)
#13000000
0"
0#
1$
0&
0'
1(
#14000000
#15000000
0!
0%
