milicar_1218_16/8/ram.vhdl
library ieee;
use ieee.std_logic_1164.all;
use ieee.numeric_std.all;

entity ram is port (
    address : in std_logic_vector (3 downto 0);
    clock, w_r : in std_logic;
    data_in : in std_logic_vector (7 downto 0);
    data_out : out std_logic_vector (7 downto 0)
);
end ram;

architecture ram_beh of ram is 

    type ram_type is array (15 downto 0) of std_logic_vector(7 downto 0); -- 16x8 = 128b
    signal ram_pom : ram_type := (others => (others => '0'));
    signal read_address : integer range 0 to 15 := 0;
    signal write_enable : std_logic := '0'; -- Promenjen tip na std_logic
    signal write_data : std_logic_vector(7 downto 0) := (others => '0');
    
begin
    process(clock)
    begin
        if rising_edge(clock) then   
            read_address <= to_integer(unsigned(address));
            write_enable <= w_r;
            if write_enable = '1' then -- Provera za aktiviranje upisa
                ram_pom(read_address) <= data_in;
            end if;
        end if;   
    end process;
    
    data_out <= ram_pom(read_address);   
end ram_beh;

milicar_1218_16/8/ram_testbench.vhdl
library ieee;
use ieee.std_logic_1164.all;

entity ram_testbench is
end ram_testbench;

architecture tb of ram_testbench is
    component ram is
        port (
            address : in std_logic_vector (3 downto 0);
            clock, w_r : in std_logic;
            data_in : in std_logic_vector (7 downto 0);
            data_out : out std_logic_vector (7 downto 0)
        );
    end component;
    
    signal clk_in, w_r_in : std_logic := '0';
    signal dat_in, dat_out : std_logic_vector(7 downto 0);
    signal add_in : std_logic_vector(3 downto 0) := "0000";
    
begin
    dut: ram port map(add_in, clk_in, w_r_in, dat_in, dat_out);
    
    process
    begin
        dat_in <= "00000000";
        add_in <= "0000";
        clk_in <= '0';
        w_r_in <= '0';
        wait for 1 ns;

        clk_in <= '1';
        wait for 1 ns;

        clk_in <= '0';
        w_r_in <= '1';
        wait for 1 ns;

        clk_in <= '1';
        wait for 1 ns;

        clk_in <= '0';
        dat_in <= "00000010";
        add_in <= "0001";
        wait for 1 ns;

        clk_in <= '1';
        wait for 1 ns;

        clk_in <= '0';
        dat_in <= "00101010";
        add_in <= "0010";
        wait for 1 ns;

        clk_in <= '1';
        wait for 1 ns;

        clk_in <= '0';
        dat_in <= "00000010";
        add_in <= "0011";
        wait for 1 ns;

        clk_in <= '1';
        wait for 1 ns;

        clk_in <= '0';
        dat_in <= "00000010";
        add_in <= "0100";
        wait for 1 ns;

        clk_in <= '1';
        wait for 1 ns;

        clk_in <= '0';
        dat_in <= "01010110";
        add_in <= "0101";
        wait for 1 ns;

        clk_in <= '1';
        wait for 1 ns;

        clk_in <= '0';
        dat_in <= "01011111";
        add_in <= "0110";
        wait for 1 ns;

        clk_in <= '1';
        wait for 1 ns;

        clk_in <= '0';
        dat_in <= "00010001";
        add_in <= "0111";
        wait for 1 ns;

        clk_in <= '1';
        wait for 1 ns;

        clk_in <= '0';
        dat_in <= "00010001";
        add_in <= "1000";
        wait for 1 ns;

        clk_in <= '1';
        wait for 1 ns;

        clk_in <= '0';
        dat_in <= "00010111";
        add_in <= "1001";
        wait for 1 ns;
     
        clk_in <= '1';
        wait for 1 ns;

        clk_in <= '0';
        w_r_in <= '0';
        add_in <= "0001";
        wait for 1 ns;

        clk_in <= '1';
        wait for 1 ns;

        clk_in <= '0';
        add_in <= "0010";
        wait for 1 ns;

        clk_in <= '1';
        wait for 1 ns;

        clk_in <= '0';
        add_in <= "0011";
        wait for 1 ns;

        clk_in <= '1';
        wait for 1 ns;

        clk_in <= '0';
        wait for 1 ns;

        wait;
    end process;
end tb;

milicar_1218_16/8/moj_Test_vcd.vcd
$date
  Tue Sep 12 19:54:17 2023
$end
$version
  GHDL v0
$end
$timescale
  1 fs
$end
$scope module standard $end
$upscope $end
$scope module std_logic_1164 $end
$upscope $end
$scope module numeric_std $end
$upscope $end
$scope module ram_testbench $end
$var reg 1 ! clk_in $end
$var reg 1 " w_r_in $end
$var reg 8 # dat_in[7:0] $end
$var reg 8 $ dat_out[7:0] $end
$var reg 4 % add_in[3:0] $end
$scope module dut $end
$var reg 4 & address[3:0] $end
$var reg 1 ' clock $end
$var reg 1 ( w_r $end
$var reg 8 ) data_in[7:0] $end
$var reg 8 * data_out[7:0] $end
$comment ram_pom is not handled $end
$var integer 32 + read_address $end
$var reg 1 , write_enable $end
$var reg 8 - write_data[7:0] $end
$upscope $end
$upscope $end
$enddefinitions $end
#0
0!
0"
b00000000 #
b00000000 $
b0000 %
b0000 &
0'
0(
b00000000 )
b00000000 *
b0 +
0,
b00000000 -
#1000000
1!
1'
#2000000
0!
1"
0'
1(
#3000000
1!
1'
1,
#4000000
0!
b00000010 #
b0001 %
b0001 &
0'
b00000010 )
#5000000
1!
1'
b1 +
#6000000
0!
b00101010 #
b0010 %
b0010 &
0'
b00101010 )
#7000000
1!
1'
b10 +
#8000000
0!
b00000010 #
b0011 %
b0011 &
0'
b00000010 )
#9000000
1!
1'
b11 +
#10000000
0!
b0100 %
b0100 &
0'
#11000000
1!
1'
b100 +
#12000000
0!
b01010110 #
b0101 %
b0101 &
0'
b01010110 )
#13000000
1!
1'
b101 +
#14000000
0!
b01011111 #
b0110 %
b0110 &
0'
b01011111 )
#15000000
1!
1'
b110 +
#16000000
0!
b00010001 #
b0111 %
b0111 &
0'
b00010001 )
#17000000
1!
1'
b111 +
#18000000
0!
b1000 %
b1000 &
0'
#19000000
1!
1'
b1000 +
#20000000
0!
b00010111 #
b1001 %
b1001 &
0'
b00010111 )
#21000000
1!
1'
b1001 +
#22000000
0!
0"
b0001 %
b0001 &
0'
0(
#23000000
1!
b00101010 $
1'
b00101010 *
b1 +
0,
#24000000
0!
b0010 %
b0010 &
0'
#25000000
1!
b00000010 $
1'
b00000010 *
b10 +
#26000000
0!
b0011 %
b0011 &
0'
#27000000
1!
1'
b11 +
