nikolab1213_20/vjezba8/ram.vhdl
library ieee;
use ieee.std_logic_1164.all;
use ieee.numeric_std.all;

entity ram is
port(
    clk, we, oe : in std_logic;
    data_in : in std_logic_vector(7 downto 0);
    address : in std_logic_vector(6 downto 0);
    data_out : out std_logic_vector(7 downto 0)
);
end ram;

architecture ram_beh of ram is
    type memorija is array(0 to 127) of std_logic_vector(7 downto 0);
    signal podaci : memorija;
    signal index : integer := 0;
begin
    process(clk)
    begin
        if(rising_edge(clk)) then
            index <= to_integer(unsigned(address));
            if (oe = '1') then
                data_out <= podaci(index);
            elsif (we = '1') then
                podaci(index) <= data_in;
            end if;
        end if;
    end process;
end ram_beh;

nikolab1213_20/vjezba8/ram_tb.vhdl
library ieee;
use ieee.std_logic_1164.all;
use ieee.numeric_std.all;

entity ram_testbench is
end ram_testbench;

architecture ram_tb of ram_testbench is
    component ram is
        port(
            clk, we, oe : in std_logic;
            data_in : in std_logic_vector(7 downto 0);
            address : in std_logic_vector(6 downto 0);
            data_out : out std_logic_vector(7 downto 0)
        );
    end component;

    signal clk1, we1, oe1 : std_logic;
    signal data_in1 : std_logic_vector(7 downto 0);
    signal address1 : std_logic_vector(6 downto 0);
    signal data_out1 :  std_logic_vector(7 downto 0);

begin
    DUT: ram port map(
        clk => clk1,
        we => we1,
        oe => oe1,
        data_in => data_in1,
        address => address1,
        data_out => data_out1
    );

    process begin

        clk1 <= '0';
        we1 <= '1';
        wait for 1 ns;
        for i in 0 to 127 loop
            address1 <= std_logic_vector(to_unsigned(i, address1'length));
            data_in1 <= std_logic_vector(to_unsigned(i, data_in1'length));
            clk1 <= '1';
            wait for 1 ns;
            clk1 <= '0';
            wait for 1 ns;
        end loop;
        we1 <= '0';
        oe1 <= '1';
        for i in 0 to 127 loop
            address1 <= std_logic_vector(to_unsigned(i, address1'length));
            clk1 <= '1';
            wait for 1 ns;
            assert(i = to_integer(unsigned(data_out1))) report "Greska - i = " & integer'image(i) severity error;
            clk1 <= '0';
            wait for 1 ns;
        end loop;
        assert false report "Test finished" severity note;
        wait;

end process;
end ram_tb;

nikolab1213_20/vjezba8/ram.vcd
$date
  Fri Aug 18 15:32:53 2023
$end
$version
  GHDL v0
$end
$timescale
  1 fs
$end
$scope module standard $end
$upscope $end
$scope module std_logic_1164 $end
$upscope $end
$scope module numeric_std $end
$upscope $end
$scope module ram_testbench $end
$var reg 1 ! clk1 $end
$var reg 1 " we1 $end
$var reg 1 # oe1 $end
$var reg 8 $ data_in1[7:0] $end
$var reg 7 % address1[6:0] $end
$var reg 8 & data_out1[7:0] $end
$scope module dut $end
$var reg 1 ' clk $end
$var reg 1 ( we $end
$var reg 1 ) oe $end
$var reg 8 * data_in[7:0] $end
$var reg 7 + address[6:0] $end
$var reg 8 , data_out[7:0] $end
$comment podaci is not handled $end
$var integer 32 - index $end
$upscope $end
$upscope $end
$enddefinitions $end
#0
0!
1"
U#
bUUUUUUUU $
bUUUUUUU %
bUUUUUUUU &
0'
1(
U)
bUUUUUUUU *
bUUUUUUU +
bUUUUUUUU ,
b0 -
#1000000
1!
b00000000 $
b0000000 %
1'
b00000000 *
b0000000 +
#2000000
0!
0'
#3000000
1!
b00000001 $
b0000001 %
1'
b00000001 *
b0000001 +
b1 -
#4000000
0!
0'
#5000000
1!
b00000010 $
b0000010 %
1'
b00000010 *
b0000010 +
b10 -
#6000000
0!
0'
#7000000
1!
b00000011 $
b0000011 %
1'
b00000011 *
b0000011 +
b11 -
#8000000
0!
0'
#9000000
1!
b00000100 $
b0000100 %
1'
b00000100 *
b0000100 +
b100 -
#10000000
0!
0'
#11000000
1!
b00000101 $
b0000101 %
1'
b00000101 *
b0000101 +
b101 -
#12000000
0!
0'
#13000000
1!
b00000110 $
b0000110 %
1'
b00000110 *
b0000110 +
b110 -
#14000000
0!
0'
#15000000
1!
b00000111 $
b0000111 %
1'
b00000111 *
b0000111 +
b111 -
#16000000
0!
0'
#17000000
1!
b00001000 $
b0001000 %
1'
b00001000 *
b0001000 +
b1000 -
#18000000
0!
0'
#19000000
1!
b00001001 $
b0001001 %
1'
b00001001 *
b0001001 +
b1001 -
#20000000
0!
0'
#21000000
1!
b00001010 $
b0001010 %
1'
b00001010 *
b0001010 +
b1010 -
#22000000
0!
0'
#23000000
1!
b00001011 $
b0001011 %
1'
b00001011 *
b0001011 +
b1011 -
#24000000
0!
0'
#25000000
1!
b00001100 $
b0001100 %
1'
b00001100 *
b0001100 +
b1100 -
#26000000
0!
0'
#27000000
1!
b00001101 $
b0001101 %
1'
b00001101 *
b0001101 +
b1101 -
#28000000
0!
0'
#29000000
1!
b00001110 $
b0001110 %
1'
b00001110 *
b0001110 +
b1110 -
#30000000
0!
0'
#31000000
1!
b00001111 $
b0001111 %
1'
b00001111 *
b0001111 +
b1111 -
#32000000
0!
0'
#33000000
1!
b00010000 $
b0010000 %
1'
b00010000 *
b0010000 +
b10000 -
#34000000
0!
0'
#35000000
1!
b00010001 $
b0010001 %
1'
b00010001 *
b0010001 +
b10001 -
#36000000
0!
0'
#37000000
1!
b00010010 $
b0010010 %
1'
b00010010 *
b0010010 +
b10010 -
#38000000
0!
0'
#39000000
1!
b00010011 $
b0010011 %
1'
b00010011 *
b0010011 +
b10011 -
#40000000
0!
0'
#41000000
1!
b00010100 $
b0010100 %
1'
b00010100 *
b0010100 +
b10100 -
#42000000
0!
0'
#43000000
1!
b00010101 $
b0010101 %
1'
b00010101 *
b0010101 +
b10101 -
#44000000
0!
0'
#45000000
1!
b00010110 $
b0010110 %
1'
b00010110 *
b0010110 +
b10110 -
#46000000
0!
0'
#47000000
1!
b00010111 $
b0010111 %
1'
b00010111 *
b0010111 +
b10111 -
#48000000
0!
0'
#49000000
1!
b00011000 $
b0011000 %
1'
b00011000 *
b0011000 +
b11000 -
#50000000
0!
0'
#51000000
1!
b00011001 $
b0011001 %
1'
b00011001 *
b0011001 +
b11001 -
#52000000
0!
0'
#53000000
1!
b00011010 $
b0011010 %
1'
b00011010 *
b0011010 +
b11010 -
#54000000
0!
0'
#55000000
1!
b00011011 $
b0011011 %
1'
b00011011 *
b0011011 +
b11011 -
#56000000
0!
0'
#57000000
1!
b00011100 $
b0011100 %
1'
b00011100 *
b0011100 +
b11100 -
#58000000
0!
0'
#59000000
1!
b00011101 $
b0011101 %
1'
b00011101 *
b0011101 +
b11101 -
#60000000
0!
0'
#61000000
1!
b00011110 $
b0011110 %
1'
b00011110 *
b0011110 +
b11110 -
#62000000
0!
0'
#63000000
1!
b00011111 $
b0011111 %
1'
b00011111 *
b0011111 +
b11111 -
#64000000
0!
0'
#65000000
1!
b00100000 $
b0100000 %
1'
b00100000 *
b0100000 +
b100000 -
#66000000
0!
0'
#67000000
1!
b00100001 $
b0100001 %
1'
b00100001 *
b0100001 +
b100001 -
#68000000
0!
0'
#69000000
1!
b00100010 $
b0100010 %
1'
b00100010 *
b0100010 +
b100010 -
#70000000
0!
0'
#71000000
1!
b00100011 $
b0100011 %
1'
b00100011 *
b0100011 +
b100011 -
#72000000
0!
0'
#73000000
1!
b00100100 $
b0100100 %
1'
b00100100 *
b0100100 +
b100100 -
#74000000
0!
0'
#75000000
1!
b00100101 $
b0100101 %
1'
b00100101 *
b0100101 +
b100101 -
#76000000
0!
0'
#77000000
1!
b00100110 $
b0100110 %
1'
b00100110 *
b0100110 +
b100110 -
#78000000
0!
0'
#79000000
1!
b00100111 $
b0100111 %
1'
b00100111 *
b0100111 +
b100111 -
#80000000
0!
0'
#81000000
1!
b00101000 $
b0101000 %
1'
b00101000 *
b0101000 +
b101000 -
#82000000
0!
0'
#83000000
1!
b00101001 $
b0101001 %
1'
b00101001 *
b0101001 +
b101001 -
#84000000
0!
0'
#85000000
1!
b00101010 $
b0101010 %
1'
b00101010 *
b0101010 +
b101010 -
#86000000
0!
0'
#87000000
1!
b00101011 $
b0101011 %
1'
b00101011 *
b0101011 +
b101011 -
#88000000
0!
0'
#89000000
1!
b00101100 $
b0101100 %
1'
b00101100 *
b0101100 +
b101100 -
#90000000
0!
0'
#91000000
1!
b00101101 $
b0101101 %
1'
b00101101 *
b0101101 +
b101101 -
#92000000
0!
0'
#93000000
1!
b00101110 $
b0101110 %
1'
b00101110 *
b0101110 +
b101110 -
#94000000
0!
0'
#95000000
1!
b00101111 $
b0101111 %
1'
b00101111 *
b0101111 +
b101111 -
#96000000
0!
0'
#97000000
1!
b00110000 $
b0110000 %
1'
b00110000 *
b0110000 +
b110000 -
#98000000
0!
0'
#99000000
1!
b00110001 $
b0110001 %
1'
b00110001 *
b0110001 +
b110001 -
#100000000
0!
0'
#101000000
1!
b00110010 $
b0110010 %
1'
b00110010 *
b0110010 +
b110010 -
#102000000
0!
0'
#103000000
1!
b00110011 $
b0110011 %
1'
b00110011 *
b0110011 +
b110011 -
#104000000
0!
0'
#105000000
1!
b00110100 $
b0110100 %
1'
b00110100 *
b0110100 +
b110100 -
#106000000
0!
0'
#107000000
1!
b00110101 $
b0110101 %
1'
b00110101 *
b0110101 +
b110101 -
#108000000
0!
0'
#109000000
1!
b00110110 $
b0110110 %
1'
b00110110 *
b0110110 +
b110110 -
#110000000
0!
0'
#111000000
1!
b00110111 $
b0110111 %
1'
b00110111 *
b0110111 +
b110111 -
#112000000
0!
0'
#113000000
1!
b00111000 $
b0111000 %
1'
b00111000 *
b0111000 +
b111000 -
#114000000
0!
0'
#115000000
1!
b00111001 $
b0111001 %
1'
b00111001 *
b0111001 +
b111001 -
#116000000
0!
0'
#117000000
1!
b00111010 $
b0111010 %
1'
b00111010 *
b0111010 +
b111010 -
#118000000
0!
0'
#119000000
1!
b00111011 $
b0111011 %
1'
b00111011 *
b0111011 +
b111011 -
#120000000
0!
0'
#121000000
1!
b00111100 $
b0111100 %
1'
b00111100 *
b0111100 +
b111100 -
#122000000
0!
0'
#123000000
1!
b00111101 $
b0111101 %
1'
b00111101 *
b0111101 +
b111101 -
#124000000
0!
0'
#125000000
1!
b00111110 $
b0111110 %
1'
b00111110 *
b0111110 +
b111110 -
#126000000
0!
0'
#127000000
1!
b00111111 $
b0111111 %
1'
b00111111 *
b0111111 +
b111111 -
#128000000
0!
0'
#129000000
1!
b01000000 $
b1000000 %
1'
b01000000 *
b1000000 +
b1000000 -
#130000000
0!
0'
#131000000
1!
b01000001 $
b1000001 %
1'
b01000001 *
b1000001 +
b1000001 -
#132000000
0!
0'
#133000000
1!
b01000010 $
b1000010 %
1'
b01000010 *
b1000010 +
b1000010 -
#134000000
0!
0'
#135000000
1!
b01000011 $
b1000011 %
1'
b01000011 *
b1000011 +
b1000011 -
#136000000
0!
0'
#137000000
1!
b01000100 $
b1000100 %
1'
b01000100 *
b1000100 +
b1000100 -
#138000000
0!
0'
#139000000
1!
b01000101 $
b1000101 %
1'
b01000101 *
b1000101 +
b1000101 -
#140000000
0!
0'
#141000000
1!
b01000110 $
b1000110 %
1'
b01000110 *
b1000110 +
b1000110 -
#142000000
0!
0'
#143000000
1!
b01000111 $
b1000111 %
1'
b01000111 *
b1000111 +
b1000111 -
#144000000
0!
0'
#145000000
1!
b01001000 $
b1001000 %
1'
b01001000 *
b1001000 +
b1001000 -
#146000000
0!
0'
#147000000
1!
b01001001 $
b1001001 %
1'
b01001001 *
b1001001 +
b1001001 -
#148000000
0!
0'
#149000000
1!
b01001010 $
b1001010 %
1'
b01001010 *
b1001010 +
b1001010 -
#150000000
0!
0'
#151000000
1!
b01001011 $
b1001011 %
1'
b01001011 *
b1001011 +
b1001011 -
#152000000
0!
0'
#153000000
1!
b01001100 $
b1001100 %
1'
b01001100 *
b1001100 +
b1001100 -
#154000000
0!
0'
#155000000
1!
b01001101 $
b1001101 %
1'
b01001101 *
b1001101 +
b1001101 -
#156000000
0!
0'
#157000000
1!
b01001110 $
b1001110 %
1'
b01001110 *
b1001110 +
b1001110 -
#158000000
0!
0'
#159000000
1!
b01001111 $
b1001111 %
1'
b01001111 *
b1001111 +
b1001111 -
#160000000
0!
0'
#161000000
1!
b01010000 $
b1010000 %
1'
b01010000 *
b1010000 +
b1010000 -
#162000000
0!
0'
#163000000
1!
b01010001 $
b1010001 %
1'
b01010001 *
b1010001 +
b1010001 -
#164000000
0!
0'
#165000000
1!
b01010010 $
b1010010 %
1'
b01010010 *
b1010010 +
b1010010 -
#166000000
0!
0'
#167000000
1!
b01010011 $
b1010011 %
1'
b01010011 *
b1010011 +
b1010011 -
#168000000
0!
0'
#169000000
1!
b01010100 $
b1010100 %
1'
b01010100 *
b1010100 +
b1010100 -
#170000000
0!
0'
#171000000
1!
b01010101 $
b1010101 %
1'
b01010101 *
b1010101 +
b1010101 -
#172000000
0!
0'
#173000000
1!
b01010110 $
b1010110 %
1'
b01010110 *
b1010110 +
b1010110 -
#174000000
0!
0'
#175000000
1!
b01010111 $
b1010111 %
1'
b01010111 *
b1010111 +
b1010111 -
#176000000
0!
0'
#177000000
1!
b01011000 $
b1011000 %
1'
b01011000 *
b1011000 +
b1011000 -
#178000000
0!
0'
#179000000
1!
b01011001 $
b1011001 %
1'
b01011001 *
b1011001 +
b1011001 -
#180000000
0!
0'
#181000000
1!
b01011010 $
b1011010 %
1'
b01011010 *
b1011010 +
b1011010 -
#182000000
0!
0'
#183000000
1!
b01011011 $
b1011011 %
1'
b01011011 *
b1011011 +
b1011011 -
#184000000
0!
0'
#185000000
1!
b01011100 $
b1011100 %
1'
b01011100 *
b1011100 +
b1011100 -
#186000000
0!
0'
#187000000
1!
b01011101 $
b1011101 %
1'
b01011101 *
b1011101 +
b1011101 -
#188000000
0!
0'
#189000000
1!
b01011110 $
b1011110 %
1'
b01011110 *
b1011110 +
b1011110 -
#190000000
0!
0'
#191000000
1!
b01011111 $
b1011111 %
1'
b01011111 *
b1011111 +
b1011111 -
#192000000
0!
0'
#193000000
1!
b01100000 $
b1100000 %
1'
b01100000 *
b1100000 +
b1100000 -
#194000000
0!
0'
#195000000
1!
b01100001 $
b1100001 %
1'
b01100001 *
b1100001 +
b1100001 -
#196000000
0!
0'
#197000000
1!
b01100010 $
b1100010 %
1'
b01100010 *
b1100010 +
b1100010 -
#198000000
0!
0'
#199000000
1!
b01100011 $
b1100011 %
1'
b01100011 *
b1100011 +
b1100011 -
#200000000
0!
0'
#201000000
1!
b01100100 $
b1100100 %
1'
b01100100 *
b1100100 +
b1100100 -
#202000000
0!
0'
#203000000
1!
b01100101 $
b1100101 %
1'
b01100101 *
b1100101 +
b1100101 -
#204000000
0!
0'
#205000000
1!
b01100110 $
b1100110 %
1'
b01100110 *
b1100110 +
b1100110 -
#206000000
0!
0'
#207000000
1!
b01100111 $
b1100111 %
1'
b01100111 *
b1100111 +
b1100111 -
#208000000
0!
0'
#209000000
1!
b01101000 $
b1101000 %
1'
b01101000 *
b1101000 +
b1101000 -
#210000000
0!
0'
#211000000
1!
b01101001 $
b1101001 %
1'
b01101001 *
b1101001 +
b1101001 -
#212000000
0!
0'
#213000000
1!
b01101010 $
b1101010 %
1'
b01101010 *
b1101010 +
b1101010 -
#214000000
0!
0'
#215000000
1!
b01101011 $
b1101011 %
1'
b01101011 *
b1101011 +
b1101011 -
#216000000
0!
0'
#217000000
1!
b01101100 $
b1101100 %
1'
b01101100 *
b1101100 +
b1101100 -
#218000000
0!
0'
#219000000
1!
b01101101 $
b1101101 %
1'
b01101101 *
b1101101 +
b1101101 -
#220000000
0!
0'
#221000000
1!
b01101110 $
b1101110 %
1'
b01101110 *
b1101110 +
b1101110 -
#222000000
0!
0'
#223000000
1!
b01101111 $
b1101111 %
1'
b01101111 *
b1101111 +
b1101111 -
#224000000
0!
0'
#225000000
1!
b01110000 $
b1110000 %
1'
b01110000 *
b1110000 +
b1110000 -
#226000000
0!
0'
#227000000
1!
b01110001 $
b1110001 %
1'
b01110001 *
b1110001 +
b1110001 -
#228000000
0!
0'
#229000000
1!
b01110010 $
b1110010 %
1'
b01110010 *
b1110010 +
b1110010 -
#230000000
0!
0'
#231000000
1!
b01110011 $
b1110011 %
1'
b01110011 *
b1110011 +
b1110011 -
#232000000
0!
0'
#233000000
1!
b01110100 $
b1110100 %
1'
b01110100 *
b1110100 +
b1110100 -
#234000000
0!
0'
#235000000
1!
b01110101 $
b1110101 %
1'
b01110101 *
b1110101 +
b1110101 -
#236000000
0!
0'
#237000000
1!
b01110110 $
b1110110 %
1'
b01110110 *
b1110110 +
b1110110 -
#238000000
0!
0'
#239000000
1!
b01110111 $
b1110111 %
1'
b01110111 *
b1110111 +
b1110111 -
#240000000
0!
0'
#241000000
1!
b01111000 $
b1111000 %
1'
b01111000 *
b1111000 +
b1111000 -
#242000000
0!
0'
#243000000
1!
b01111001 $
b1111001 %
1'
b01111001 *
b1111001 +
b1111001 -
#244000000
0!
0'
#245000000
1!
b01111010 $
b1111010 %
1'
b01111010 *
b1111010 +
b1111010 -
#246000000
0!
0'
#247000000
1!
b01111011 $
b1111011 %
1'
b01111011 *
b1111011 +
b1111011 -
#248000000
0!
0'
#249000000
1!
b01111100 $
b1111100 %
1'
b01111100 *
b1111100 +
b1111100 -
#250000000
0!
0'
#251000000
1!
b01111101 $
b1111101 %
1'
b01111101 *
b1111101 +
b1111101 -
#252000000
0!
0'
#253000000
1!
b01111110 $
b1111110 %
1'
b01111110 *
b1111110 +
b1111110 -
#254000000
0!
0'
#255000000
1!
b01111111 $
b1111111 %
1'
b01111111 *
b1111111 +
b1111111 -
#256000000
0!
0'
#257000000
1!
0"
1#
b0000000 %
1'
0(
1)
b0000000 +
b0 -
#258000000
0!
0'
#259000000
1!
b0000001 %
b00000001 &
1'
b0000001 +
b00000001 ,
b1 -
#260000000
0!
0'
#261000000
1!
b0000010 %
b00000010 &
1'
b0000010 +
b00000010 ,
b10 -
#262000000
0!
0'
#263000000
1!
b0000011 %
b00000011 &
1'
b0000011 +
b00000011 ,
b11 -
#264000000
0!
0'
#265000000
1!
b0000100 %
b00000100 &
1'
b0000100 +
b00000100 ,
b100 -
#266000000
0!
0'
#267000000
1!
b0000101 %
b00000101 &
1'
b0000101 +
b00000101 ,
b101 -
#268000000
0!
0'
#269000000
1!
b0000110 %
b00000110 &
1'
b0000110 +
b00000110 ,
b110 -
#270000000
0!
0'
#271000000
1!
b0000111 %
b00000111 &
1'
b0000111 +
b00000111 ,
b111 -
#272000000
0!
0'
#273000000
1!
b0001000 %
b00001000 &
1'
b0001000 +
b00001000 ,
b1000 -
#274000000
0!
0'
#275000000
1!
b0001001 %
b00001001 &
1'
b0001001 +
b00001001 ,
b1001 -
#276000000
0!
0'
#277000000
1!
b0001010 %
b00001010 &
1'
b0001010 +
b00001010 ,
b1010 -
#278000000
0!
0'
#279000000
1!
b0001011 %
b00001011 &
1'
b0001011 +
b00001011 ,
b1011 -
#280000000
0!
0'
#281000000
1!
b0001100 %
b00001100 &
1'
b0001100 +
b00001100 ,
b1100 -
#282000000
0!
0'
#283000000
1!
b0001101 %
b00001101 &
1'
b0001101 +
b00001101 ,
b1101 -
#284000000
0!
0'
#285000000
1!
b0001110 %
b00001110 &
1'
b0001110 +
b00001110 ,
b1110 -
#286000000
0!
0'
#287000000
1!
b0001111 %
b00001111 &
1'
b0001111 +
b00001111 ,
b1111 -
#288000000
0!
0'
#289000000
1!
b0010000 %
b00010000 &
1'
b0010000 +
b00010000 ,
b10000 -
#290000000
0!
0'
#291000000
1!
b0010001 %
b00010001 &
1'
b0010001 +
b00010001 ,
b10001 -
#292000000
0!
0'
#293000000
1!
b0010010 %
b00010010 &
1'
b0010010 +
b00010010 ,
b10010 -
#294000000
0!
0'
#295000000
1!
b0010011 %
b00010011 &
1'
b0010011 +
b00010011 ,
b10011 -
#296000000
0!
0'
#297000000
1!
b0010100 %
b00010100 &
1'
b0010100 +
b00010100 ,
b10100 -
#298000000
0!
0'
#299000000
1!
b0010101 %
b00010101 &
1'
b0010101 +
b00010101 ,
b10101 -
#300000000
0!
0'
#301000000
1!
b0010110 %
b00010110 &
1'
b0010110 +
b00010110 ,
b10110 -
#302000000
0!
0'
#303000000
1!
b0010111 %
b00010111 &
1'
b0010111 +
b00010111 ,
b10111 -
#304000000
0!
0'
#305000000
1!
b0011000 %
b00011000 &
1'
b0011000 +
b00011000 ,
b11000 -
#306000000
0!
0'
#307000000
1!
b0011001 %
b00011001 &
1'
b0011001 +
b00011001 ,
b11001 -
#308000000
0!
0'
#309000000
1!
b0011010 %
b00011010 &
1'
b0011010 +
b00011010 ,
b11010 -
#310000000
0!
0'
#311000000
1!
b0011011 %
b00011011 &
1'
b0011011 +
b00011011 ,
b11011 -
#312000000
0!
0'
#313000000
1!
b0011100 %
b00011100 &
1'
b0011100 +
b00011100 ,
b11100 -
#314000000
0!
0'
#315000000
1!
b0011101 %
b00011101 &
1'
b0011101 +
b00011101 ,
b11101 -
#316000000
0!
0'
#317000000
1!
b0011110 %
b00011110 &
1'
b0011110 +
b00011110 ,
b11110 -
#318000000
0!
0'
#319000000
1!
b0011111 %
b00011111 &
1'
b0011111 +
b00011111 ,
b11111 -
#320000000
0!
0'
#321000000
1!
b0100000 %
b00100000 &
1'
b0100000 +
b00100000 ,
b100000 -
#322000000
0!
0'
#323000000
1!
b0100001 %
b00100001 &
1'
b0100001 +
b00100001 ,
b100001 -
#324000000
0!
0'
#325000000
1!
b0100010 %
b00100010 &
1'
b0100010 +
b00100010 ,
b100010 -
#326000000
0!
0'
#327000000
1!
b0100011 %
b00100011 &
1'
b0100011 +
b00100011 ,
b100011 -
#328000000
0!
0'
#329000000
1!
b0100100 %
b00100100 &
1'
b0100100 +
b00100100 ,
b100100 -
#330000000
0!
0'
#331000000
1!
b0100101 %
b00100101 &
1'
b0100101 +
b00100101 ,
b100101 -
#332000000
0!
0'
#333000000
1!
b0100110 %
b00100110 &
1'
b0100110 +
b00100110 ,
b100110 -
#334000000
0!
0'
#335000000
1!
b0100111 %
b00100111 &
1'
b0100111 +
b00100111 ,
b100111 -
#336000000
0!
0'
#337000000
1!
b0101000 %
b00101000 &
1'
b0101000 +
b00101000 ,
b101000 -
#338000000
0!
0'
#339000000
1!
b0101001 %
b00101001 &
1'
b0101001 +
b00101001 ,
b101001 -
#340000000
0!
0'
#341000000
1!
b0101010 %
b00101010 &
1'
b0101010 +
b00101010 ,
b101010 -
#342000000
0!
0'
#343000000
1!
b0101011 %
b00101011 &
1'
b0101011 +
b00101011 ,
b101011 -
#344000000
0!
0'
#345000000
1!
b0101100 %
b00101100 &
1'
b0101100 +
b00101100 ,
b101100 -
#346000000
0!
0'
#347000000
1!
b0101101 %
b00101101 &
1'
b0101101 +
b00101101 ,
b101101 -
#348000000
0!
0'
#349000000
1!
b0101110 %
b00101110 &
1'
b0101110 +
b00101110 ,
b101110 -
#350000000
0!
0'
#351000000
1!
b0101111 %
b00101111 &
1'
b0101111 +
b00101111 ,
b101111 -
#352000000
0!
0'
#353000000
1!
b0110000 %
b00110000 &
1'
b0110000 +
b00110000 ,
b110000 -
#354000000
0!
0'
#355000000
1!
b0110001 %
b00110001 &
1'
b0110001 +
b00110001 ,
b110001 -
#356000000
0!
0'
#357000000
1!
b0110010 %
b00110010 &
1'
b0110010 +
b00110010 ,
b110010 -
#358000000
0!
0'
#359000000
1!
b0110011 %
b00110011 &
1'
b0110011 +
b00110011 ,
b110011 -
#360000000
0!
0'
#361000000
1!
b0110100 %
b00110100 &
1'
b0110100 +
b00110100 ,
b110100 -
#362000000
0!
0'
#363000000
1!
b0110101 %
b00110101 &
1'
b0110101 +
b00110101 ,
b110101 -
#364000000
0!
0'
#365000000
1!
b0110110 %
b00110110 &
1'
b0110110 +
b00110110 ,
b110110 -
#366000000
0!
0'
#367000000
1!
b0110111 %
b00110111 &
1'
b0110111 +
b00110111 ,
b110111 -
#368000000
0!
0'
#369000000
1!
b0111000 %
b00111000 &
1'
b0111000 +
b00111000 ,
b111000 -
#370000000
0!
0'
#371000000
1!
b0111001 %
b00111001 &
1'
b0111001 +
b00111001 ,
b111001 -
#372000000
0!
0'
#373000000
1!
b0111010 %
b00111010 &
1'
b0111010 +
b00111010 ,
b111010 -
#374000000
0!
0'
#375000000
1!
b0111011 %
b00111011 &
1'
b0111011 +
b00111011 ,
b111011 -
#376000000
0!
0'
#377000000
1!
b0111100 %
b00111100 &
1'
b0111100 +
b00111100 ,
b111100 -
#378000000
0!
0'
#379000000
1!
b0111101 %
b00111101 &
1'
b0111101 +
b00111101 ,
b111101 -
#380000000
0!
0'
#381000000
1!
b0111110 %
b00111110 &
1'
b0111110 +
b00111110 ,
b111110 -
#382000000
0!
0'
#383000000
1!
b0111111 %
b00111111 &
1'
b0111111 +
b00111111 ,
b111111 -
#384000000
0!
0'
#385000000
1!
b1000000 %
b01000000 &
1'
b1000000 +
b01000000 ,
b1000000 -
#386000000
0!
0'
#387000000
1!
b1000001 %
b01000001 &
1'
b1000001 +
b01000001 ,
b1000001 -
#388000000
0!
0'
#389000000
1!
b1000010 %
b01000010 &
1'
b1000010 +
b01000010 ,
b1000010 -
#390000000
0!
0'
#391000000
1!
b1000011 %
b01000011 &
1'
b1000011 +
b01000011 ,
b1000011 -
#392000000
0!
0'
#393000000
1!
b1000100 %
b01000100 &
1'
b1000100 +
b01000100 ,
b1000100 -
#394000000
0!
0'
#395000000
1!
b1000101 %
b01000101 &
1'
b1000101 +
b01000101 ,
b1000101 -
#396000000
0!
0'
#397000000
1!
b1000110 %
b01000110 &
1'
b1000110 +
b01000110 ,
b1000110 -
#398000000
0!
0'
#399000000
1!
b1000111 %
b01000111 &
1'
b1000111 +
b01000111 ,
b1000111 -
#400000000
0!
0'
#401000000
1!
b1001000 %
b01001000 &
1'
b1001000 +
b01001000 ,
b1001000 -
#402000000
0!
0'
#403000000
1!
b1001001 %
b01001001 &
1'
b1001001 +
b01001001 ,
b1001001 -
#404000000
0!
0'
#405000000
1!
b1001010 %
b01001010 &
1'
b1001010 +
b01001010 ,
b1001010 -
#406000000
0!
0'
#407000000
1!
b1001011 %
b01001011 &
1'
b1001011 +
b01001011 ,
b1001011 -
#408000000
0!
0'
#409000000
1!
b1001100 %
b01001100 &
1'
b1001100 +
b01001100 ,
b1001100 -
#410000000
0!
0'
#411000000
1!
b1001101 %
b01001101 &
1'
b1001101 +
b01001101 ,
b1001101 -
#412000000
0!
0'
#413000000
1!
b1001110 %
b01001110 &
1'
b1001110 +
b01001110 ,
b1001110 -
#414000000
0!
0'
#415000000
1!
b1001111 %
b01001111 &
1'
b1001111 +
b01001111 ,
b1001111 -
#416000000
0!
0'
#417000000
1!
b1010000 %
b01010000 &
1'
b1010000 +
b01010000 ,
b1010000 -
#418000000
0!
0'
#419000000
1!
b1010001 %
b01010001 &
1'
b1010001 +
b01010001 ,
b1010001 -
#420000000
0!
0'
#421000000
1!
b1010010 %
b01010010 &
1'
b1010010 +
b01010010 ,
b1010010 -
#422000000
0!
0'
#423000000
1!
b1010011 %
b01010011 &
1'
b1010011 +
b01010011 ,
b1010011 -
#424000000
0!
0'
#425000000
1!
b1010100 %
b01010100 &
1'
b1010100 +
b01010100 ,
b1010100 -
#426000000
0!
0'
#427000000
1!
b1010101 %
b01010101 &
1'
b1010101 +
b01010101 ,
b1010101 -
#428000000
0!
0'
#429000000
1!
b1010110 %
b01010110 &
1'
b1010110 +
b01010110 ,
b1010110 -
#430000000
0!
0'
#431000000
1!
b1010111 %
b01010111 &
1'
b1010111 +
b01010111 ,
b1010111 -
#432000000
0!
0'
#433000000
1!
b1011000 %
b01011000 &
1'
b1011000 +
b01011000 ,
b1011000 -
#434000000
0!
0'
#435000000
1!
b1011001 %
b01011001 &
1'
b1011001 +
b01011001 ,
b1011001 -
#436000000
0!
0'
#437000000
1!
b1011010 %
b01011010 &
1'
b1011010 +
b01011010 ,
b1011010 -
#438000000
0!
0'
#439000000
1!
b1011011 %
b01011011 &
1'
b1011011 +
b01011011 ,
b1011011 -
#440000000
0!
0'
#441000000
1!
b1011100 %
b01011100 &
1'
b1011100 +
b01011100 ,
b1011100 -
#442000000
0!
0'
#443000000
1!
b1011101 %
b01011101 &
1'
b1011101 +
b01011101 ,
b1011101 -
#444000000
0!
0'
#445000000
1!
b1011110 %
b01011110 &
1'
b1011110 +
b01011110 ,
b1011110 -
#446000000
0!
0'
#447000000
1!
b1011111 %
b01011111 &
1'
b1011111 +
b01011111 ,
b1011111 -
#448000000
0!
0'
#449000000
1!
b1100000 %
b01100000 &
1'
b1100000 +
b01100000 ,
b1100000 -
#450000000
0!
0'
#451000000
1!
b1100001 %
b01100001 &
1'
b1100001 +
b01100001 ,
b1100001 -
#452000000
0!
0'
#453000000
1!
b1100010 %
b01100010 &
1'
b1100010 +
b01100010 ,
b1100010 -
#454000000
0!
0'
#455000000
1!
b1100011 %
b01100011 &
1'
b1100011 +
b01100011 ,
b1100011 -
#456000000
0!
0'
#457000000
1!
b1100100 %
b01100100 &
1'
b1100100 +
b01100100 ,
b1100100 -
#458000000
0!
0'
#459000000
1!
b1100101 %
b01100101 &
1'
b1100101 +
b01100101 ,
b1100101 -
#460000000
0!
0'
#461000000
1!
b1100110 %
b01100110 &
1'
b1100110 +
b01100110 ,
b1100110 -
#462000000
0!
0'
#463000000
1!
b1100111 %
b01100111 &
1'
b1100111 +
b01100111 ,
b1100111 -
#464000000
0!
0'
#465000000
1!
b1101000 %
b01101000 &
1'
b1101000 +
b01101000 ,
b1101000 -
#466000000
0!
0'
#467000000
1!
b1101001 %
b01101001 &
1'
b1101001 +
b01101001 ,
b1101001 -
#468000000
0!
0'
#469000000
1!
b1101010 %
b01101010 &
1'
b1101010 +
b01101010 ,
b1101010 -
#470000000
0!
0'
#471000000
1!
b1101011 %
b01101011 &
1'
b1101011 +
b01101011 ,
b1101011 -
#472000000
0!
0'
