milicar_1218_16/3/jk_flipflop.vhdl
library ieee;
use ieee.std_logic_1164.all;
use ieee.numeric_std.all;
	
entity jk_flipflop is
	port
	(
		-- Input ports
		j	: in  std_logic;
		k	: in  std_logic;
		clk	: in  std_logic;
        reset : in std_logic;
		-- Output ports
		q	: out std_logic
	);
end jk_flipflop;

architecture jk_flipflop_arch of jk_flipflop is

signal qn : std_logic;

begin

process(clk,reset)
begin
if(reset='1') then 
    qn<='0';
elsif (rising_edge(clk)) then
	if (j='0' and k='0') then
		qn<=qn;
	elsif (j='0' and k='1') then
		qn<='0';
	elsif (j='1' and k='0') then
		qn<='1';
	else
		qn<=not qn;
	end if;
end if;

end process;

q<=qn;

end jk_flipflop_arch;

milicar_1218_16/3/jk_flipflop/jk_flipflop_testbench.vhdl
library IEEE;
use IEEE.std_logic_1164.all;

entity testbench is
end testbench;

architecture tb of testbench is
    component jk_flipflop is
        port
        (
            -- Input ports
            j	: in  std_logic;
            k	: in  std_logic;
            clk	: in  std_logic;
            reset: in std_logic;
    
            -- Output ports
            q	: out std_logic
        );
    end component;
    
signal j_test : std_logic;
signal k_test : std_logic;
signal clk_test : std_logic;
signal reset_test : std_logic;
signal q_test : std_logic;
signal i:integer:=0;
constant num_of_clks : integer:= 10;

begin
 DUT: jk_flipflop port map(j_test,k_test,clk_test,reset_test,q_test);
 process 
 begin
    clk_test <= '1';
    wait for 0.5 ns;
    clk_test <= '0';
    wait for 0.5 ns;

    if(i=num_of_clks) then 
        wait;
    else 
        i <= i+1;
    end if;

    end process;

 process
 begin
 j_test <= '0';
 k_test <= '0';
 wait for 1 ns;
 --assert(q_test=q) report "Fail 0/0" severity error;

 j_test <= '0';
 k_test <= '1';
 wait for 1 ns;
 --assert(q_test='0') report "Fail 0/1" severity error;

 j_test <= '1';
 k_test <= '0';
 wait for 1 ns;
 --assert(q_test='1') report "Fail 1/X" severity error;

 j_test <= '1';
 k_test <= '1';
 wait for 1 ns;
 --assert(q_test=not q) report "Fail 1/1" severity error;

 
 --assert false report "Test done." severity note;
 wait;
 end process;

 reset_test <= '1' , '0' after 4 ns;
end tb;

milicar_1218_16/3/jk_flipflop/moj_Test_vcd.vcd
$date
  Mon Sep 11 18:02:04 2023
$end
$version
  GHDL v0
$end
$timescale
  1 fs
$end
$scope module standard $end
$upscope $end
$scope module std_logic_1164 $end
$upscope $end
$scope module numeric_std $end
$upscope $end
$scope module testbench $end
$var reg 1 ! j_test $end
$var reg 1 " k_test $end
$var reg 1 # clk_test $end
$var reg 1 $ reset_test $end
$var reg 1 % q_test $end
$var integer 32 & i $end
$scope module dut $end
$var reg 1 ' j $end
$var reg 1 ( k $end
$var reg 1 ) clk $end
$var reg 1 * reset $end
$var reg 1 + q $end
$var reg 1 , qn $end
$upscope $end
$upscope $end
$enddefinitions $end
#0
0!
0"
1#
1$
0%
b0 &
0'
0(
1)
1*
0+
0,
#500000
0#
0)
#1000000
1"
1#
b1 &
1(
1)
#1500000
0#
0)
#2000000
1!
0"
1#
b10 &
1'
0(
1)
#2500000
0#
0)
#3000000
1"
1#
b11 &
1(
1)
#3500000
0#
0)
#4000000
1#
0$
1%
b100 &
1)
0*
1+
1,
#4500000
0#
0)
#5000000
1#
0%
b101 &
1)
0+
0,
#5500000
0#
0)
#6000000
1#
1%
b110 &
1)
1+
1,
#6500000
0#
0)
#7000000
1#
0%
b111 &
1)
0+
0,
#7500000
0#
0)
#8000000
1#
1%
b1000 &
1)
1+
1,
#8500000
0#
0)
#9000000
1#
0%
b1001 &
1)
0+
0,
#9500000
0#
0)
#10000000
1#
1%
b1010 &
1)
1+
1,
