milicar_1218_16/3/t_flipflop/t_flipflop.vhdl
library ieee;
use ieee.std_logic_1164.all;
use ieee.numeric_std.all;

entity t_flipflop is
    port 
    (
        clk : in std_logic;
        t : in std_logic;
        reset : in std_logic;
        q : out std_logic
    );
end t_flipflop;

architecture t_flipflop_arch of t_flipflop is
    signal t_sig : std_logic;  
begin 
process(clk,reset)
begin
if(reset = '1') then 
    t_sig <= '0';
elsif (rising_edge(clk)) then
    if (t='1') then
        t_sig <= not t_sig;
    else
        t_sig <= t_sig;
    end if;
end if;      
end process;

q<=t_sig;

end t_flipflop_arch;

milicar_1218_16/3/t_flipflop/t_flipflop_testbench.vhdl
library ieee;
use ieee.std_logic_1164.all;
use ieee.numeric_std.all;

entity t_testbench is 
end t_testbench;

architecture t_arch of t_testbench is
component t_flipflop is
    port 
    (
        clk : in std_logic;
        t : in std_logic;
        reset : in std_logic;
        q : out std_logic
    );
end component;
signal clk_test : std_logic;
signal t_test : std_logic;
signal reset_test : std_logic;
signal q_test : std_logic;
signal i:integer:=0;
constant num_of_clks : integer:= 10;

begin
DUT: t_flipflop port map(clk_test,t_test, reset_test,q_test);

process
begin 
clk_test <= '1';
wait for 0.5 ns;
clk_test <= '0';
wait for 0.5 ns;

if(i=num_of_clks) then 
    wait;
else 
    i <= i+1;
end if;
end process;

process
begin 
t_test <= '0';
wait for 1 ns;
--assert((q_test='0' and reset_test='0') or (q_test='0' and reset_test='1')) report "Fail" severity error;

t_test <= '1';
wait for 1 ns;
--assert((q_test='1' and reset_test='0') or (q_test='0' and reset_test='1')) report "Fail" severity error;

t_test <= '1';
wait for 3 ns;
--assert((q_test='1' and reset_test='0') or (q_test='0' and reset_test='1')) report "Fail" severity error;

t_test <= '0';
wait for 1 ns;
--assert((q_test='0' and reset_test='0') or (q_test='0' and reset_test='1')) report "Fail" severity error;

wait;
end process;

reset_test <= '1' , '0' after 2 ns;

end t_arch;

milicar_1218_16/3/t_flipflop/moj_Test_vcd.vcd
$date
  Mon Sep 11 20:54:42 2023
$end
$version
  GHDL v0
$end
$timescale
  1 fs
$end
$scope module standard $end
$upscope $end
$scope module std_logic_1164 $end
$upscope $end
$scope module numeric_std $end
$upscope $end
$scope module t_testbench $end
$var reg 1 ! clk_test $end
$var reg 1 " t_test $end
$var reg 1 # reset_test $end
$var reg 1 $ q_test $end
$var integer 32 % i $end
$scope module dut $end
$var reg 1 & clk $end
$var reg 1 ' t $end
$var reg 1 ( reset $end
$var reg 1 ) q $end
$var reg 1 * t_sig $end
$upscope $end
$upscope $end
$enddefinitions $end
#0
1!
0"
1#
0$
b0 %
1&
0'
1(
0)
0*
#500000
0!
0&
#1000000
1!
1"
b1 %
1&
1'
#1500000
0!
0&
#2000000
1!
0#
1$
b10 %
1&
0(
1)
1*
#2500000
0!
0&
#3000000
1!
0$
b11 %
1&
0)
0*
#3500000
0!
0&
#4000000
1!
1$
b100 %
1&
1)
1*
#4500000
0!
0&
#5000000
1!
0"
b101 %
1&
0'
#5500000
0!
0&
#6000000
1!
b110 %
1&
#6500000
0!
0&
#7000000
1!
b111 %
1&
#7500000
0!
0&
#8000000
1!
b1000 %
1&
#8500000
0!
0&
#9000000
1!
b1001 %
1&
#9500000
0!
0&
#10000000
1!
b1010 %
1&
