radislavkosijer1152_19/vjezba3/RS_flipflop.vhdl
library ieee;
use ieee.std_logic_1164.all;

entity RS_flipflop is
    port(
        S, R, CP : in std_logic;
        Q, Qnot : out std_logic
    );
end RS_flipflop;

architecture RS_flipflop_beh of RS_flipflop is
    signal pom : std_logic := '1';
begin
    RS_flipflop_proc: process(CP)
    begin
        if falling_edge(CP) then
        if(S = '1' and R = '0') then
            pom <= '1';
        elsif (S = '0' and R = '1') then
            pom <= '0';
        elsif (S = '1' and R = '1') then
                pom <= 'X';
        end if;
        end if;
    end process RS_flipflop_proc;
Q <= pom;
Qnot <= not pom;
end RS_flipflop_beh;

radislavkosijer1152_19/vjezba3/RS_flipflop_testbench.vhdl
library ieee;
use ieee.std_logic_1164.all;

entity RS_flipflop_tb is
end RS_flipflop_tb;

architecture RS_testbench_beh of RS_flipflop_tb is

    component RS_flipflop is
        port(
            S, R, CP : in std_logic;
            Q, Qnot : out std_logic
        );
    end component;

    signal S_in: std_logic := '1';
    signal R_in: std_logic := '0';
    signal CP_in: std_logic := '1';
    signal Q_out: std_logic := '1';
    signal Qnot_out: std_logic := '0';

    begin

        DUT: RS_flipflop port map(S_in, R_in, CP_in, Q_out, Qnot_out);

        process
        begin

            wait for 1 ns;
            CP_in <= '0';
            wait for 1 ns;
            assert(Q_out = '1' and Qnot_out = '0') report "Neispravan izlaz kada je S na visokom nivou" severity error;

            CP_in <= '1';
            R_in <= '1';
            S_in <= '0';
            wait for 1 ns;
            CP_in <= '0';
            wait for 1 ns;
            assert(Q_out = '0' and Qnot_out = '1') report "Neispravan izlaz kada je R na visokom nivou" severity error;

            CP_in <= '1';
            S_in <= '0';
            R_in <= '0';
            wait for 1 ns;
            CP_in <= '0';
            wait for 1 ns;
            assert(Q_out = '0' and Qnot_out = '1') report "Izlaz nije zadrzao prethodno stanje kada su S i R na niskom nivou" severity error;

            CP_in <= '1';
            S_in <= '1';
            R_in <= '1';
            wait for 1 ns;
            CP_in <= '0';
            wait for 1 ns;
            assert(Q_out = 'X' and Qnot_out = 'X') report "Izlaz nije nedefinisan kada su S i R na visokom nivou" severity error;
            

            assert false report "Test zavrsen!" severity note;
            wait;
            end process;
 end RS_testbench_beh;

radislavkosijer1152_19/vjezba3/RS_flipflop_vcd.vcd
$date
  Wed Sep 13 14:52:24 2023
$end
$version
  GHDL v0
$end
$timescale
  1 fs
$end
$scope module standard $end
$upscope $end
$scope module std_logic_1164 $end
$upscope $end
$scope module rs_flipflop_tb $end
$var reg 1 ! s_in $end
$var reg 1 " r_in $end
$var reg 1 # cp_in $end
$var reg 1 $ q_out $end
$var reg 1 % qnot_out $end
$scope module dut $end
$var reg 1 & s $end
$var reg 1 ' r $end
$var reg 1 ( cp $end
$var reg 1 ) q $end
$var reg 1 * qnot $end
$var reg 1 + pom $end
$upscope $end
$upscope $end
$enddefinitions $end
#0
1!
0"
1#
1$
0%
1&
0'
1(
1)
0*
1+
#1000000
0#
0(
#2000000
0!
1"
1#
0&
1'
1(
#3000000
0#
0$
1%
0(
0)
1*
0+
#4000000
0"
1#
0'
1(
#5000000
0#
0(
#6000000
1!
1"
1#
1&
1'
1(
#7000000
0#
X$
X%
0(
X)
X*
X+
