milicar_1218_16/3/rs_flipflop.vhdl
library ieee;
use ieee.std_logic_1164.all;
use ieee.numeric_std.all;
	
entity rs_flipflop is
	port
	(
		-- Input ports
		r	: in  std_logic;
		s	: in  std_logic;
		clk	: in  std_logic;
        reset : in std_logic;
		-- Output ports
		q	: out std_logic
	);
end rs_flipflop;

architecture rs_flipflop_arch of rs_flipflop is

signal qn : std_logic;

begin

process(clk,reset)
begin
if(reset='1') then 
    qn<='0';
elsif (rising_edge(clk)) then
	if (r='0' and s='0') then
		qn<=qn;
	elsif (r='0' and s='1') then
		qn<='1';
	elsif (r='1' and s='0') then
		qn<='0';
	else
		qn <= 'X';
	end if;
end if;

end process;

q<=qn;

end rs_flipflop_arch;

milicar_1218_16/3/rs_flipflop/rs_flipflop_testbench.vhdl
library IEEE;
use IEEE.std_logic_1164.all;

entity testbench is
end testbench;

architecture tb of testbench is
    component rs_flipflop is
        port
        (
            -- Input ports
            r	: in  std_logic;
            s	: in  std_logic;
            clk	: in  std_logic;
            reset: in std_logic;
    
            -- Output ports
            q	: out std_logic
        );
    end component;
    
signal r_test : std_logic;
signal s_test : std_logic;
signal clk_test : std_logic;
signal reset_test : std_logic;
signal q_test : std_logic;
signal i:integer:=0;
constant num_of_clks : integer:= 10;

begin
 DUT: rs_flipflop port map(r_test,s_test,clk_test,reset_test,q_test);
 process 
 begin
    clk_test <= '1';
    wait for 0.5 ns;
    clk_test <= '0';
    wait for 0.5 ns;

    if(i=num_of_clks) then 
        wait;
    else 
        i <= i+1;
    end if;

    end process;

 process
 begin
 r_test <= '0';
 s_test <= '0';
 wait for 1 ns;
 --assert(q_test=q) report "Fail 0/0" severity error;

 r_test <= '0';
 s_test <= '1';
 wait for 1 ns;
 --assert(q_test='0') report "Fail 0/1" severity error;

 r_test <= '1';
 s_test <= '0';
 wait for 1 ns;
 --assert(q_test='1') report "Fail 1/X" severity error;

 r_test <= '1';
 s_test <= '1';
 wait for 1 ns;
 --assert(q_test=not q) report "Fail 1/1" severity error;

 
 --assert false report "Test done." severity note;
 wait;
 end process;

 reset_test <= '0' , '1' after 5 ns;
end tb;

milicar_1218_16/3/rs_flipflop/moj_Test_vcd.vcd
$date
  Mon Sep 11 18:40:33 2023
$end
$version
  GHDL v0
$end
$timescale
  1 fs
$end
$scope module standard $end
$upscope $end
$scope module std_logic_1164 $end
$upscope $end
$scope module numeric_std $end
$upscope $end
$scope module testbench $end
$var reg 1 ! r_test $end
$var reg 1 " s_test $end
$var reg 1 # clk_test $end
$var reg 1 $ reset_test $end
$var reg 1 % q_test $end
$var integer 32 & i $end
$scope module dut $end
$var reg 1 ' r $end
$var reg 1 ( s $end
$var reg 1 ) clk $end
$var reg 1 * reset $end
$var reg 1 + q $end
$var reg 1 , qn $end
$upscope $end
$upscope $end
$enddefinitions $end
#0
0!
0"
1#
0$
U%
b0 &
0'
0(
1)
0*
U+
U,
#500000
0#
0)
#1000000
1"
1#
1%
b1 &
1(
1)
1+
1,
#1500000
0#
0)
#2000000
1!
0"
1#
0%
b10 &
1'
0(
1)
0+
0,
#2500000
0#
0)
#3000000
1"
1#
X%
b11 &
1(
1)
X+
X,
#3500000
0#
0)
#4000000
1#
b100 &
1)
#4500000
0#
0)
#5000000
1#
1$
0%
b101 &
1)
1*
0+
0,
#5500000
0#
0)
#6000000
1#
b110 &
1)
#6500000
0#
0)
#7000000
1#
b111 &
1)
#7500000
0#
0)
#8000000
1#
b1000 &
1)
#8500000
0#
0)
#9000000
1#
b1001 &
1)
#9500000
0#
0)
#10000000
1#
b1010 &
1)
