milicar_1218_16/6/stacionarni_reg.vhdl
library ieee;
use ieee.std_logic_1164.all;

entity stacionarni_reg is
    port (
        clk, clr, ld: in std_logic;
        data_in: in std_logic_vector(9 downto 0);
        data_out: out std_logic_vector(9 downto 0)
    );
end entity stacionarni_reg;

architecture stacionarni_reg_beh of stacionarni_reg is
    signal stanje: std_logic_vector(9 downto 0) := "0000000000";
begin
    process(clk, clr, ld)
    begin
        if clr = '1' then
            stanje <= "0000000000";
        elsif rising_edge(clk) then
            if ld = '1' then
                stanje <= data_in;
            end if;
        end if;
    end process;
    
    data_out <= stanje;
end stacionarni_reg_beh;

milicar_1218_16/6/tb_stacionarni_reg.vhdl
library IEEE;
use IEEE.std_logic_1164.all;

entity tb_stacionarni_reg is
end tb_stacionarni_reg;

architecture tb of tb_stacionarni_reg is
  component stacionarni_reg is
    port (
      clk, clr, ld: in std_logic;
      data_in: in std_logic_vector(9 downto 0);
      data_out: out std_logic_vector(9 downto 0)
    );
  end component;
  
  signal clk_in, clr_in, ld_in: std_logic;
  signal dat_in, dat_out: std_logic_vector(9 downto 0);

begin
  DUT: stacionarni_reg port map(clk_in, clr_in, ld_in, dat_in, dat_out);
  
  process
  begin
    dat_in <= "0000000000";
    clk_in <= '0';
    clr_in <= '1';
    ld_in <= '0';
    wait for 1 ns;

    clr_in <= '0';
    clk_in <= '1';
    wait for 100 ps;
    ld_in <= '1';
    wait for 900 ps;

    dat_in <= "0000000001";
    clk_in <= '0';
    wait for 100 ps;
    ld_in <= '0';
    wait for 100 ps;
    ld_in <= '1';
    wait for 800 ps;

    dat_in <= "0000000100";
    clk_in <= '1';
    wait for 100 ps;
    ld_in <= '0';
    wait for 100 ps;
    ld_in <= '1';
    wait for 800 ps;

    dat_in <= "0010010010";
    clk_in <= '0';
    wait for 100 ps;
    ld_in <= '0';
    wait for 100 ps;
    ld_in <= '1';
    wait for 800 ps;

    dat_in <= "0101001010";
    clk_in <= '1';
    wait for 100 ps;
    ld_in <= '0';
    wait for 100 ps;
    ld_in <= '1';
    wait for 800 ps;

    clr_in <= '1';
    dat_in <= "1010101001";
    ld_in <= '0';
    clk_in <= '0';

    wait;
  end process;
end tb;

milicar_1218_16/6/Stacionarni registar/moj_Test_vcd.vcd
$date
  Tue Sep 12 14:40:21 2023
$end
$version
  GHDL v0
$end
$timescale
  1 fs
$end
$scope module standard $end
$upscope $end
$scope module std_logic_1164 $end
$upscope $end
$scope module tb_stacionarni_reg $end
$var reg 1 ! clk_in $end
$var reg 1 " clr_in $end
$var reg 1 # ld_in $end
$var reg 10 $ dat_in[9:0] $end
$var reg 10 % dat_out[9:0] $end
$scope module dut $end
$var reg 1 & clk $end
$var reg 1 ' clr $end
$var reg 1 ( ld $end
$var reg 10 ) data_in[9:0] $end
$var reg 10 * data_out[9:0] $end
$var reg 10 + stanje[9:0] $end
$upscope $end
$upscope $end
$enddefinitions $end
#0
0!
1"
0#
b0000000000 $
b0000000000 %
0&
1'
0(
b0000000000 )
b0000000000 *
b0000000000 +
#1000000
1!
0"
1&
0'
#1100000
1#
1(
#2000000
0!
b0000000001 $
0&
b0000000001 )
#2100000
0#
0(
#2200000
1#
1(
#3000000
1!
b0000000100 $
b0000000100 %
1&
b0000000100 )
b0000000100 *
b0000000100 +
#3100000
0#
0(
#3200000
1#
1(
#4000000
0!
b0010010010 $
0&
b0010010010 )
#4100000
0#
0(
#4200000
1#
1(
#5000000
1!
b0101001010 $
b0101001010 %
1&
b0101001010 )
b0101001010 *
b0101001010 +
#5100000
0#
0(
#5200000
1#
1(
#6000000
0!
1"
0#
b1010101001 $
b0000000000 %
0&
1'
0(
b1010101001 )
b0000000000 *
b0000000000 +
