milicar_1218_16/6/Pomjeracki registar/Pomjeracki_Registar.vhdl
library ieee;
use ieee.std_logic_1164.all;
use ieee.numeric_std.all;

entity Pomjeracki_Registar is
    port (
        clk, rst, rin, lin : in std_logic;
        mode : in std_logic_vector(1 downto 0);
        data_in : in std_logic_vector(5 downto 0);
        data_out : out std_logic_vector(5 downto 0)
    );
end entity Pomjeracki_Registar;

architecture p_reg_arch of Pomjeracki_Registar is
    signal trenutno_stanje, prethodno_stanje : std_logic_vector(5 downto 0);
begin
    process(clk, rst)
    begin
        prethodno_stanje <= trenutno_stanje;
        if rst = '0' then
            trenutno_stanje <= "000000";
        elsif rising_edge(clk) then
            case mode is
                when "00" =>
                    trenutno_stanje <= trenutno_stanje; -- Nema promene
                when "01" =>
                    trenutno_stanje <= data_in; -- Paralelan upis
                when "10" =>
                    trenutno_stanje(0) <= rin;
                    for j in 1 to 5 loop
                        trenutno_stanje(j) <= prethodno_stanje(j-1); -- Pomak u levo
                    end loop;
                when "11" =>
                    trenutno_stanje(5) <= lin;
                    for j in 0 to 4 loop
                        trenutno_stanje(j) <= prethodno_stanje(j+1); -- Pomak u desno
                    end loop;
                when others =>
                    trenutno_stanje <= "000000";
            end case;
        end if;
    end process;

    data_out <= trenutno_stanje;
end p_reg_arch;

milicar_1218_16/6/Pomjeracki registar/TestBenchPReg.vhdl
library IEEE;
use IEEE.std_logic_1164.all;

entity TestBenchPReg is
end TestBenchPReg;

architecture tb_arch of TestBenchPReg is
    component Pomjeracki_Registar is
        port (
            clk, rst, rin, lin : in std_logic;
            mode : in std_logic_vector(1 downto 0);
            data_in : in std_logic_vector(5 downto 0);
            data_out : out std_logic_vector(5 downto 0)
        );
    end component;

    signal clk_in, rst_in, rin_in, lin_in : std_logic;
    signal mode_in : std_logic_vector(1 downto 0);
    signal data_in, data_out : std_logic_vector(5 downto 0);
begin
    
    DUT: Pomjeracki_Registar port map(clk_in, rst_in, rin_in, lin_in, mode_in, data_in, data_out);

    process
    begin
        clk_in <= '0';
        rst_in <= '1';
        rin_in <= '0';
        lin_in <= '1';
        mode_in <= "01";
        data_in <= "011010";
        wait for 1 ns;

        clk_in <= '1';
        wait for 1 ns;

        clk_in <= '0';
        mode_in <= "00";
        wait for 1 ns;

        clk_in <= '1';
        wait for 1 ns;

        clk_in <= '0';
        mode_in <= "10";
        wait for 1 ns;

        clk_in <= '1';
        wait for 1 ns;

        clk_in <= '0';
        wait for 1 ns;

        clk_in <= '1';
        wait for 1 ns;

        clk_in <= '0';
        wait for 1 ns;

        clk_in <= '1';
        wait for 1 ns;

        clk_in <= '0';
        mode_in <= "11";
        wait for 1 ns;

        clk_in <= '1';
        wait for 1 ns;

        clk_in <= '0';
        wait for 1 ns;

        clk_in <= '1';
        wait for 1 ns;

        clk_in <= '0';
        wait for 1 ns;

        clk_in <= '1';
        wait for 1 ns;

        clk_in <= '0';
        rst_in <= '0';
        wait for 1 ns;

        clk_in <= '1';
        wait for 1 ns;

        clk_in <= '0';
        wait for 1 ns;

        clk_in <= '1';
        wait for 1 ns;

        wait;
    end process;
end tb_arch;

milicar_1218_16/6/Pomjeracki registar/moj_Test_vcd.vcd
$date
  Tue Sep 12 14:03:19 2023
$end
$version
  GHDL v0
$end
$timescale
  1 fs
$end
$scope module standard $end
$upscope $end
$scope module std_logic_1164 $end
$upscope $end
$scope module numeric_std $end
$upscope $end
$scope module testbenchpreg $end
$var reg 1 ! clk_in $end
$var reg 1 " rst_in $end
$var reg 1 # rin_in $end
$var reg 1 $ lin_in $end
$var reg 2 % mode_in[1:0] $end
$var reg 6 & data_in[5:0] $end
$var reg 6 ' data_out[5:0] $end
$scope module dut $end
$var reg 1 ( clk $end
$var reg 1 ) rst $end
$var reg 1 * rin $end
$var reg 1 + lin $end
$var reg 2 , mode[1:0] $end
$var reg 6 - data_in[5:0] $end
$var reg 6 . data_out[5:0] $end
$var reg 6 / trenutno_stanje[5:0] $end
$var reg 6 0 prethodno_stanje[5:0] $end
$upscope $end
$upscope $end
$enddefinitions $end
#0
0!
1"
0#
1$
b01 %
b011010 &
bUUUUUU '
0(
1)
0*
1+
b01 ,
b011010 -
bUUUUUU .
bUUUUUU /
bUUUUUU 0
#1000000
1!
b011010 '
1(
b011010 .
b011010 /
#2000000
0!
b00 %
0(
b00 ,
b011010 0
#3000000
1!
1(
#4000000
0!
b10 %
0(
b10 ,
#5000000
1!
b110100 '
1(
b110100 .
b110100 /
#6000000
0!
0(
b110100 0
#7000000
1!
b101000 '
1(
b101000 .
b101000 /
#8000000
0!
0(
b101000 0
#9000000
1!
b010000 '
1(
b010000 .
b010000 /
#10000000
0!
b11 %
0(
b11 ,
b010000 0
#11000000
1!
b101000 '
1(
b101000 .
b101000 /
#12000000
0!
0(
b101000 0
#13000000
1!
b110100 '
1(
b110100 .
b110100 /
#14000000
0!
0(
b110100 0
#15000000
1!
b111010 '
1(
b111010 .
b111010 /
#16000000
0!
0"
b000000 '
0(
0)
b000000 .
b000000 /
b111010 0
#17000000
1!
1(
b000000 0
