radislavkosijer1152_19/vjezba8/ram.vhdl
library ieee;
use ieee.std_logic_1164.all;
use IEEE.numeric_std.all;

entity RAM is
generic(
    memory_size : integer := 128;
    word_size : integer := 8;
    address_size : integer := 7
);
port(
    CLK, RW : in std_logic; --RW = '1' upis podataka, RW = '0' citanje podataka
    ADDRESS : in std_logic_vector(address_size-1 downto 0);
    DATA_IN : in std_logic_vector (word_size-1 downto 0);
    DATA_OUT : out std_logic_vector (word_size-1 downto 0)
);
end entity RAM;

architecture arh_RAM of RAM is

    type RAM_memory is array(0 to memory_size-1) of std_logic_vector(word_size-1 downto 0);
    signal mem : RAM_memory;

begin
    process(CLK)
    begin
        if(rising_edge(CLK)) then
            if(RW = '0') then
                DATA_OUT <= mem(to_integer(unsigned(ADDRESS)));
            elsif(RW = '1') then
                mem(to_integer(unsigned(ADDRESS))) <= DATA_IN;
            end if;
        end if;
    end process;
end architecture arh_RAM;

radislavkosijer1152_19/vjezba8/ram_tb.vhdl
library ieee;
use ieee.std_logic_1164.all;
use IEEE.numeric_std.all;

entity RAM_tb is
end entity RAM_tb;

architecture arh_RAM_tb of RAM_tb is

    component RAM is
        generic(
            memory_size : integer := 128;
            word_size : integer := 8;
            address_size : integer := 7
        );
        port(
            CLK, RW : in std_logic; 
            ADDRESS : in std_logic_vector(address_size-1 downto 0);
            DATA_IN : in std_logic_vector (word_size-1 downto 0);
            DATA_OUT : out std_logic_vector (word_size-1 downto 0)
        );
    end component RAM;

    constant memory_s : integer := 128;
    constant word_s : integer := 8;
    constant address_s : integer := 7;
  

    signal clk_in: std_logic;
    signal rw_in: std_logic := '1';
    signal address_in : std_logic_vector(address_s-1 downto 0) := "0000000";
    signal data_in_in: std_logic_vector(word_s-1 downto 0);
    signal data_out_out: std_logic_vector(word_s-1 downto 0);

begin

    DUT: RAM generic map (memory_size => memory_s, word_size => word_s, address_size => address_s) port map (CLK => clk_in, RW => rw_in, ADDRESS => address_in, DATA_IN => data_in_in, DATA_OUT => data_out_out);

    parametri: process
    begin

        data_in_in <= "00000000";
        for i in 0 to memory_s-1 loop
            clk_in <= '0';
            wait for 1 ns;
            clk_in <= '1';
            wait for 1 ns;
            data_in_in <= std_logic_vector(unsigned(data_in_in) + 1);
            address_in <= std_logic_vector(unsigned(address_in) + 1);
        end loop;

        rw_in <= '0';
        address_in <= "0000000";
        for m in 0 to memory_s-1 loop
            clk_in <= '0';
            wait for 1 ns;
            clk_in <= '1';
            wait for 1 ns;
            assert(to_integer(unsigned(data_out_out)) = m) report "Neispravan izlaz kada se vrsi ispis sa adrese m" & integer'image(m) severity error; --jer se m poklapa sa decimalnom vrijednoscu adrese kao i upisane vrijednosti
            address_in <= std_logic_vector(unsigned(address_in) + 1);
        end loop;

        assert false report "Test zavrsen!" severity note;
        wait;
    end process parametri;

end architecture arh_RAM_tb;

radislavkosijer1152_19/vjezba8/ram_vcd.vcd
$date
  Tue Sep 26 18:32:06 2023
$end
$version
  GHDL v0
$end
$timescale
  1 fs
$end
$scope module standard $end
$upscope $end
$scope module std_logic_1164 $end
$upscope $end
$scope module numeric_std $end
$upscope $end
$scope module ram_tb $end
$var reg 1 ! clk_in $end
$var reg 1 " rw_in $end
$var reg 7 # address_in[6:0] $end
$var reg 8 $ data_in_in[7:0] $end
$var reg 8 % data_out_out[7:0] $end
$scope module dut $end
$var reg 1 & clk $end
$var reg 1 ' rw $end
$var reg 7 ( address[6:0] $end
$var reg 8 ) data_in[7:0] $end
$var reg 8 * data_out[7:0] $end
$comment mem is not handled $end
$upscope $end
$upscope $end
$enddefinitions $end
#0
0!
1"
b0000000 #
b00000000 $
bUUUUUUUU %
0&
1'
b0000000 (
b00000000 )
bUUUUUUUU *
#1000000
1!
1&
#2000000
0!
b0000001 #
b00000001 $
0&
b0000001 (
b00000001 )
#3000000
1!
1&
#4000000
0!
b0000010 #
b00000010 $
0&
b0000010 (
b00000010 )
#5000000
1!
1&
#6000000
0!
b0000011 #
b00000011 $
0&
b0000011 (
b00000011 )
#7000000
1!
1&
#8000000
0!
b0000100 #
b00000100 $
0&
b0000100 (
b00000100 )
#9000000
1!
1&
#10000000
0!
b0000101 #
b00000101 $
0&
b0000101 (
b00000101 )
#11000000
1!
1&
#12000000
0!
b0000110 #
b00000110 $
0&
b0000110 (
b00000110 )
#13000000
1!
1&
#14000000
0!
b0000111 #
b00000111 $
0&
b0000111 (
b00000111 )
#15000000
1!
1&
#16000000
0!
b0001000 #
b00001000 $
0&
b0001000 (
b00001000 )
#17000000
1!
1&
#18000000
0!
b0001001 #
b00001001 $
0&
b0001001 (
b00001001 )
#19000000
1!
1&
#20000000
0!
b0001010 #
b00001010 $
0&
b0001010 (
b00001010 )
#21000000
1!
1&
#22000000
0!
b0001011 #
b00001011 $
0&
b0001011 (
b00001011 )
#23000000
1!
1&
#24000000
0!
b0001100 #
b00001100 $
0&
b0001100 (
b00001100 )
#25000000
1!
1&
#26000000
0!
b0001101 #
b00001101 $
0&
b0001101 (
b00001101 )
#27000000
1!
1&
#28000000
0!
b0001110 #
b00001110 $
0&
b0001110 (
b00001110 )
#29000000
1!
1&
#30000000
0!
b0001111 #
b00001111 $
0&
b0001111 (
b00001111 )
#31000000
1!
1&
#32000000
0!
b0010000 #
b00010000 $
0&
b0010000 (
b00010000 )
#33000000
1!
1&
#34000000
0!
b0010001 #
b00010001 $
0&
b0010001 (
b00010001 )
#35000000
1!
1&
#36000000
0!
b0010010 #
b00010010 $
0&
b0010010 (
b00010010 )
#37000000
1!
1&
#38000000
0!
b0010011 #
b00010011 $
0&
b0010011 (
b00010011 )
#39000000
1!
1&
#40000000
0!
b0010100 #
b00010100 $
0&
b0010100 (
b00010100 )
#41000000
1!
1&
#42000000
0!
b0010101 #
b00010101 $
0&
b0010101 (
b00010101 )
#43000000
1!
1&
#44000000
0!
b0010110 #
b00010110 $
0&
b0010110 (
b00010110 )
#45000000
1!
1&
#46000000
0!
b0010111 #
b00010111 $
0&
b0010111 (
b00010111 )
#47000000
1!
1&
#48000000
0!
b0011000 #
b00011000 $
0&
b0011000 (
b00011000 )
#49000000
1!
1&
#50000000
0!
b0011001 #
b00011001 $
0&
b0011001 (
b00011001 )
#51000000
1!
1&
#52000000
0!
b0011010 #
b00011010 $
0&
b0011010 (
b00011010 )
#53000000
1!
1&
#54000000
0!
b0011011 #
b00011011 $
0&
b0011011 (
b00011011 )
#55000000
1!
1&
#56000000
0!
b0011100 #
b00011100 $
0&
b0011100 (
b00011100 )
#57000000
1!
1&
#58000000
0!
b0011101 #
b00011101 $
0&
b0011101 (
b00011101 )
#59000000
1!
1&
#60000000
0!
b0011110 #
b00011110 $
0&
b0011110 (
b00011110 )
#61000000
1!
1&
#62000000
0!
b0011111 #
b00011111 $
0&
b0011111 (
b00011111 )
#63000000
1!
1&
#64000000
0!
b0100000 #
b00100000 $
0&
b0100000 (
b00100000 )
#65000000
1!
1&
#66000000
0!
b0100001 #
b00100001 $
0&
b0100001 (
b00100001 )
#67000000
1!
1&
#68000000
0!
b0100010 #
b00100010 $
0&
b0100010 (
b00100010 )
#69000000
1!
1&
#70000000
0!
b0100011 #
b00100011 $
0&
b0100011 (
b00100011 )
#71000000
1!
1&
#72000000
0!
b0100100 #
b00100100 $
0&
b0100100 (
b00100100 )
#73000000
1!
1&
#74000000
0!
b0100101 #
b00100101 $
0&
b0100101 (
b00100101 )
#75000000
1!
1&
#76000000
0!
b0100110 #
b00100110 $
0&
b0100110 (
b00100110 )
#77000000
1!
1&
#78000000
0!
b0100111 #
b00100111 $
0&
b0100111 (
b00100111 )
#79000000
1!
1&
#80000000
0!
b0101000 #
b00101000 $
0&
b0101000 (
b00101000 )
#81000000
1!
1&
#82000000
0!
b0101001 #
b00101001 $
0&
b0101001 (
b00101001 )
#83000000
1!
1&
#84000000
0!
b0101010 #
b00101010 $
0&
b0101010 (
b00101010 )
#85000000
1!
1&
#86000000
0!
b0101011 #
b00101011 $
0&
b0101011 (
b00101011 )
#87000000
1!
1&
#88000000
0!
b0101100 #
b00101100 $
0&
b0101100 (
b00101100 )
#89000000
1!
1&
#90000000
0!
b0101101 #
b00101101 $
0&
b0101101 (
b00101101 )
#91000000
1!
1&
#92000000
0!
b0101110 #
b00101110 $
0&
b0101110 (
b00101110 )
#93000000
1!
1&
#94000000
0!
b0101111 #
b00101111 $
0&
b0101111 (
b00101111 )
#95000000
1!
1&
#96000000
0!
b0110000 #
b00110000 $
0&
b0110000 (
b00110000 )
#97000000
1!
1&
#98000000
0!
b0110001 #
b00110001 $
0&
b0110001 (
b00110001 )
#99000000
1!
1&
#100000000
0!
b0110010 #
b00110010 $
0&
b0110010 (
b00110010 )
#101000000
1!
1&
#102000000
0!
b0110011 #
b00110011 $
0&
b0110011 (
b00110011 )
#103000000
1!
1&
#104000000
0!
b0110100 #
b00110100 $
0&
b0110100 (
b00110100 )
#105000000
1!
1&
#106000000
0!
b0110101 #
b00110101 $
0&
b0110101 (
b00110101 )
#107000000
1!
1&
#108000000
0!
b0110110 #
b00110110 $
0&
b0110110 (
b00110110 )
#109000000
1!
1&
#110000000
0!
b0110111 #
b00110111 $
0&
b0110111 (
b00110111 )
#111000000
1!
1&
#112000000
0!
b0111000 #
b00111000 $
0&
b0111000 (
b00111000 )
#113000000
1!
1&
#114000000
0!
b0111001 #
b00111001 $
0&
b0111001 (
b00111001 )
#115000000
1!
1&
#116000000
0!
b0111010 #
b00111010 $
0&
b0111010 (
b00111010 )
#117000000
1!
1&
#118000000
0!
b0111011 #
b00111011 $
0&
b0111011 (
b00111011 )
#119000000
1!
1&
#120000000
0!
b0111100 #
b00111100 $
0&
b0111100 (
b00111100 )
#121000000
1!
1&
#122000000
0!
b0111101 #
b00111101 $
0&
b0111101 (
b00111101 )
#123000000
1!
1&
#124000000
0!
b0111110 #
b00111110 $
0&
b0111110 (
b00111110 )
#125000000
1!
1&
#126000000
0!
b0111111 #
b00111111 $
0&
b0111111 (
b00111111 )
#127000000
1!
1&
#128000000
0!
b1000000 #
b01000000 $
0&
b1000000 (
b01000000 )
#129000000
1!
1&
#130000000
0!
b1000001 #
b01000001 $
0&
b1000001 (
b01000001 )
#131000000
1!
1&
#132000000
0!
b1000010 #
b01000010 $
0&
b1000010 (
b01000010 )
#133000000
1!
1&
#134000000
0!
b1000011 #
b01000011 $
0&
b1000011 (
b01000011 )
#135000000
1!
1&
#136000000
0!
b1000100 #
b01000100 $
0&
b1000100 (
b01000100 )
#137000000
1!
1&
#138000000
0!
b1000101 #
b01000101 $
0&
b1000101 (
b01000101 )
#139000000
1!
1&
#140000000
0!
b1000110 #
b01000110 $
0&
b1000110 (
b01000110 )
#141000000
1!
1&
#142000000
0!
b1000111 #
b01000111 $
0&
b1000111 (
b01000111 )
#143000000
1!
1&
#144000000
0!
b1001000 #
b01001000 $
0&
b1001000 (
b01001000 )
#145000000
1!
1&
#146000000
0!
b1001001 #
b01001001 $
0&
b1001001 (
b01001001 )
#147000000
1!
1&
#148000000
0!
b1001010 #
b01001010 $
0&
b1001010 (
b01001010 )
#149000000
1!
1&
#150000000
0!
b1001011 #
b01001011 $
0&
b1001011 (
b01001011 )
#151000000
1!
1&
#152000000
0!
b1001100 #
b01001100 $
0&
b1001100 (
b01001100 )
#153000000
1!
1&
#154000000
0!
b1001101 #
b01001101 $
0&
b1001101 (
b01001101 )
#155000000
1!
1&
#156000000
0!
b1001110 #
b01001110 $
0&
b1001110 (
b01001110 )
#157000000
1!
1&
#158000000
0!
b1001111 #
b01001111 $
0&
b1001111 (
b01001111 )
#159000000
1!
1&
#160000000
0!
b1010000 #
b01010000 $
0&
b1010000 (
b01010000 )
#161000000
1!
1&
#162000000
0!
b1010001 #
b01010001 $
0&
b1010001 (
b01010001 )
#163000000
1!
1&
#164000000
0!
b1010010 #
b01010010 $
0&
b1010010 (
b01010010 )
#165000000
1!
1&
#166000000
0!
b1010011 #
b01010011 $
0&
b1010011 (
b01010011 )
#167000000
1!
1&
#168000000
0!
b1010100 #
b01010100 $
0&
b1010100 (
b01010100 )
#169000000
1!
1&
#170000000
0!
b1010101 #
b01010101 $
0&
b1010101 (
b01010101 )
#171000000
1!
1&
#172000000
0!
b1010110 #
b01010110 $
0&
b1010110 (
b01010110 )
#173000000
1!
1&
#174000000
0!
b1010111 #
b01010111 $
0&
b1010111 (
b01010111 )
#175000000
1!
1&
#176000000
0!
b1011000 #
b01011000 $
0&
b1011000 (
b01011000 )
#177000000
1!
1&
#178000000
0!
b1011001 #
b01011001 $
0&
b1011001 (
b01011001 )
#179000000
1!
1&
#180000000
0!
b1011010 #
b01011010 $
0&
b1011010 (
b01011010 )
#181000000
1!
1&
#182000000
0!
b1011011 #
b01011011 $
0&
b1011011 (
b01011011 )
#183000000
1!
1&
#184000000
0!
b1011100 #
b01011100 $
0&
b1011100 (
b01011100 )
#185000000
1!
1&
#186000000
0!
b1011101 #
b01011101 $
0&
b1011101 (
b01011101 )
#187000000
1!
1&
#188000000
0!
b1011110 #
b01011110 $
0&
b1011110 (
b01011110 )
#189000000
1!
1&
#190000000
0!
b1011111 #
b01011111 $
0&
b1011111 (
b01011111 )
#191000000
1!
1&
#192000000
0!
b1100000 #
b01100000 $
0&
b1100000 (
b01100000 )
#193000000
1!
1&
#194000000
0!
b1100001 #
b01100001 $
0&
b1100001 (
b01100001 )
#195000000
1!
1&
#196000000
0!
b1100010 #
b01100010 $
0&
b1100010 (
b01100010 )
#197000000
1!
1&
#198000000
0!
b1100011 #
b01100011 $
0&
b1100011 (
b01100011 )
#199000000
1!
1&
#200000000
0!
b1100100 #
b01100100 $
0&
b1100100 (
b01100100 )
#201000000
1!
1&
#202000000
0!
b1100101 #
b01100101 $
0&
b1100101 (
b01100101 )
#203000000
1!
1&
#204000000
0!
b1100110 #
b01100110 $
0&
b1100110 (
b01100110 )
#205000000
1!
1&
#206000000
0!
b1100111 #
b01100111 $
0&
b1100111 (
b01100111 )
#207000000
1!
1&
#208000000
0!
b1101000 #
b01101000 $
0&
b1101000 (
b01101000 )
#209000000
1!
1&
#210000000
0!
b1101001 #
b01101001 $
0&
b1101001 (
b01101001 )
#211000000
1!
1&
#212000000
0!
b1101010 #
b01101010 $
0&
b1101010 (
b01101010 )
#213000000
1!
1&
#214000000
0!
b1101011 #
b01101011 $
0&
b1101011 (
b01101011 )
#215000000
1!
1&
#216000000
0!
b1101100 #
b01101100 $
0&
b1101100 (
b01101100 )
#217000000
1!
1&
#218000000
0!
b1101101 #
b01101101 $
0&
b1101101 (
b01101101 )
#219000000
1!
1&
#220000000
0!
b1101110 #
b01101110 $
0&
b1101110 (
b01101110 )
#221000000
1!
1&
#222000000
0!
b1101111 #
b01101111 $
0&
b1101111 (
b01101111 )
#223000000
1!
1&
#224000000
0!
b1110000 #
b01110000 $
0&
b1110000 (
b01110000 )
#225000000
1!
1&
#226000000
0!
b1110001 #
b01110001 $
0&
b1110001 (
b01110001 )
#227000000
1!
1&
#228000000
0!
b1110010 #
b01110010 $
0&
b1110010 (
b01110010 )
#229000000
1!
1&
#230000000
0!
b1110011 #
b01110011 $
0&
b1110011 (
b01110011 )
#231000000
1!
1&
#232000000
0!
b1110100 #
b01110100 $
0&
b1110100 (
b01110100 )
#233000000
1!
1&
#234000000
0!
b1110101 #
b01110101 $
0&
b1110101 (
b01110101 )
#235000000
1!
1&
#236000000
0!
b1110110 #
b01110110 $
0&
b1110110 (
b01110110 )
#237000000
1!
1&
#238000000
0!
b1110111 #
b01110111 $
0&
b1110111 (
b01110111 )
#239000000
1!
1&
#240000000
0!
b1111000 #
b01111000 $
0&
b1111000 (
b01111000 )
#241000000
1!
1&
#242000000
0!
b1111001 #
b01111001 $
0&
b1111001 (
b01111001 )
#243000000
1!
1&
#244000000
0!
b1111010 #
b01111010 $
0&
b1111010 (
b01111010 )
#245000000
1!
1&
#246000000
0!
b1111011 #
b01111011 $
0&
b1111011 (
b01111011 )
#247000000
1!
1&
#248000000
0!
b1111100 #
b01111100 $
0&
b1111100 (
b01111100 )
#249000000
1!
1&
#250000000
0!
b1111101 #
b01111101 $
0&
b1111101 (
b01111101 )
#251000000
1!
1&
#252000000
0!
b1111110 #
b01111110 $
0&
b1111110 (
b01111110 )
#253000000
1!
1&
#254000000
0!
b1111111 #
b01111111 $
0&
b1111111 (
b01111111 )
#255000000
1!
1&
#256000000
0!
0"
b0000000 #
b10000000 $
0&
0'
b0000000 (
b10000000 )
#257000000
1!
b00000000 %
1&
b00000000 *
#258000000
0!
b0000001 #
0&
b0000001 (
#259000000
1!
b00000001 %
1&
b00000001 *
#260000000
0!
b0000010 #
0&
b0000010 (
#261000000
1!
b00000010 %
1&
b00000010 *
#262000000
0!
b0000011 #
0&
b0000011 (
#263000000
1!
b00000011 %
1&
b00000011 *
#264000000
0!
b0000100 #
0&
b0000100 (
#265000000
1!
b00000100 %
1&
b00000100 *
#266000000
0!
b0000101 #
0&
b0000101 (
#267000000
1!
b00000101 %
1&
b00000101 *
#268000000
0!
b0000110 #
0&
b0000110 (
#269000000
1!
b00000110 %
1&
b00000110 *
#270000000
0!
b0000111 #
0&
b0000111 (
#271000000
1!
b00000111 %
1&
b00000111 *
#272000000
0!
b0001000 #
0&
b0001000 (
#273000000
1!
b00001000 %
1&
b00001000 *
#274000000
0!
b0001001 #
0&
b0001001 (
#275000000
1!
b00001001 %
1&
b00001001 *
#276000000
0!
b0001010 #
0&
b0001010 (
#277000000
1!
b00001010 %
1&
b00001010 *
#278000000
0!
b0001011 #
0&
b0001011 (
#279000000
1!
b00001011 %
1&
b00001011 *
#280000000
0!
b0001100 #
0&
b0001100 (
#281000000
1!
b00001100 %
1&
b00001100 *
#282000000
0!
b0001101 #
0&
b0001101 (
#283000000
1!
b00001101 %
1&
b00001101 *
#284000000
0!
b0001110 #
0&
b0001110 (
#285000000
1!
b00001110 %
1&
b00001110 *
#286000000
0!
b0001111 #
0&
b0001111 (
#287000000
1!
b00001111 %
1&
b00001111 *
#288000000
0!
b0010000 #
0&
b0010000 (
#289000000
1!
b00010000 %
1&
b00010000 *
#290000000
0!
b0010001 #
0&
b0010001 (
#291000000
1!
b00010001 %
1&
b00010001 *
#292000000
0!
b0010010 #
0&
b0010010 (
#293000000
1!
b00010010 %
1&
b00010010 *
#294000000
0!
b0010011 #
0&
b0010011 (
#295000000
1!
b00010011 %
1&
b00010011 *
#296000000
0!
b0010100 #
0&
b0010100 (
#297000000
1!
b00010100 %
1&
b00010100 *
#298000000
0!
b0010101 #
0&
b0010101 (
#299000000
1!
b00010101 %
1&
b00010101 *
#300000000
0!
b0010110 #
0&
b0010110 (
#301000000
1!
b00010110 %
1&
b00010110 *
#302000000
0!
b0010111 #
0&
b0010111 (
#303000000
1!
b00010111 %
1&
b00010111 *
#304000000
0!
b0011000 #
0&
b0011000 (
#305000000
1!
b00011000 %
1&
b00011000 *
#306000000
0!
b0011001 #
0&
b0011001 (
#307000000
1!
b00011001 %
1&
b00011001 *
#308000000
0!
b0011010 #
0&
b0011010 (
#309000000
1!
b00011010 %
1&
b00011010 *
#310000000
0!
b0011011 #
0&
b0011011 (
#311000000
1!
b00011011 %
1&
b00011011 *
#312000000
0!
b0011100 #
0&
b0011100 (
#313000000
1!
b00011100 %
1&
b00011100 *
#314000000
0!
b0011101 #
0&
b0011101 (
#315000000
1!
b00011101 %
1&
b00011101 *
#316000000
0!
b0011110 #
0&
b0011110 (
#317000000
1!
b00011110 %
1&
b00011110 *
#318000000
0!
b0011111 #
0&
b0011111 (
#319000000
1!
b00011111 %
1&
b00011111 *
#320000000
0!
b0100000 #
0&
b0100000 (
#321000000
1!
b00100000 %
1&
b00100000 *
#322000000
0!
b0100001 #
0&
b0100001 (
#323000000
1!
b00100001 %
1&
b00100001 *
#324000000
0!
b0100010 #
0&
b0100010 (
#325000000
1!
b00100010 %
1&
b00100010 *
#326000000
0!
b0100011 #
0&
b0100011 (
#327000000
1!
b00100011 %
1&
b00100011 *
#328000000
0!
b0100100 #
0&
b0100100 (
#329000000
1!
b00100100 %
1&
b00100100 *
#330000000
0!
b0100101 #
0&
b0100101 (
#331000000
1!
b00100101 %
1&
b00100101 *
#332000000
0!
b0100110 #
0&
b0100110 (
#333000000
1!
b00100110 %
1&
b00100110 *
#334000000
0!
b0100111 #
0&
b0100111 (
#335000000
1!
b00100111 %
1&
b00100111 *
#336000000
0!
b0101000 #
0&
b0101000 (
#337000000
1!
b00101000 %
1&
b00101000 *
#338000000
0!
b0101001 #
0&
b0101001 (
#339000000
1!
b00101001 %
1&
b00101001 *
#340000000
0!
b0101010 #
0&
b0101010 (
#341000000
1!
b00101010 %
1&
b00101010 *
#342000000
0!
b0101011 #
0&
b0101011 (
#343000000
1!
b00101011 %
1&
b00101011 *
#344000000
0!
b0101100 #
0&
b0101100 (
#345000000
1!
b00101100 %
1&
b00101100 *
#346000000
0!
b0101101 #
0&
b0101101 (
#347000000
1!
b00101101 %
1&
b00101101 *
#348000000
0!
b0101110 #
0&
b0101110 (
#349000000
1!
b00101110 %
1&
b00101110 *
#350000000
0!
b0101111 #
0&
b0101111 (
#351000000
1!
b00101111 %
1&
b00101111 *
#352000000
0!
b0110000 #
0&
b0110000 (
#353000000
1!
b00110000 %
1&
b00110000 *
#354000000
0!
b0110001 #
0&
b0110001 (
#355000000
1!
b00110001 %
1&
b00110001 *
#356000000
0!
b0110010 #
0&
b0110010 (
#357000000
1!
b00110010 %
1&
b00110010 *
#358000000
0!
b0110011 #
0&
b0110011 (
#359000000
1!
b00110011 %
1&
b00110011 *
#360000000
0!
b0110100 #
0&
b0110100 (
#361000000
1!
b00110100 %
1&
b00110100 *
#362000000
0!
b0110101 #
0&
b0110101 (
#363000000
1!
b00110101 %
1&
b00110101 *
#364000000
0!
b0110110 #
0&
b0110110 (
#365000000
1!
b00110110 %
1&
b00110110 *
#366000000
0!
b0110111 #
0&
b0110111 (
#367000000
1!
b00110111 %
1&
b00110111 *
#368000000
0!
b0111000 #
0&
b0111000 (
#369000000
1!
b00111000 %
1&
b00111000 *
#370000000
0!
b0111001 #
0&
b0111001 (
#371000000
1!
b00111001 %
1&
b00111001 *
#372000000
0!
b0111010 #
0&
b0111010 (
#373000000
1!
b00111010 %
1&
b00111010 *
#374000000
0!
b0111011 #
0&
b0111011 (
#375000000
1!
b00111011 %
1&
b00111011 *
#376000000
0!
b0111100 #
0&
b0111100 (
#377000000
1!
b00111100 %
1&
b00111100 *
#378000000
0!
b0111101 #
0&
b0111101 (
#379000000
1!
b00111101 %
1&
b00111101 *
#380000000
0!
b0111110 #
0&
b0111110 (
#381000000
1!
b00111110 %
1&
b00111110 *
#382000000
0!
b0111111 #
0&
b0111111 (
#383000000
1!
b00111111 %
1&
b00111111 *
#384000000
0!
b1000000 #
0&
b1000000 (
#385000000
1!
b01000000 %
1&
b01000000 *
#386000000
0!
b1000001 #
0&
b1000001 (
#387000000
1!
b01000001 %
1&
b01000001 *
#388000000
0!
b1000010 #
0&
b1000010 (
#389000000
1!
b01000010 %
1&
b01000010 *
#390000000
0!
b1000011 #
0&
b1000011 (
#391000000
1!
b01000011 %
1&
b01000011 *
#392000000
0!
b1000100 #
0&
b1000100 (
#393000000
1!
b01000100 %
1&
b01000100 *
#394000000
0!
b1000101 #
0&
b1000101 (
#395000000
1!
b01000101 %
1&
b01000101 *
#396000000
0!
b1000110 #
0&
b1000110 (
#397000000
1!
b01000110 %
1&
b01000110 *
#398000000
0!
b1000111 #
0&
b1000111 (
#399000000
1!
b01000111 %
1&
b01000111 *
#400000000
0!
b1001000 #
0&
b1001000 (
#401000000
1!
b01001000 %
1&
b01001000 *
#402000000
0!
b1001001 #
0&
b1001001 (
#403000000
1!
b01001001 %
1&
b01001001 *
#404000000
0!
b1001010 #
0&
b1001010 (
#405000000
1!
b01001010 %
1&
b01001010 *
#406000000
0!
b1001011 #
0&
b1001011 (
#407000000
1!
b01001011 %
1&
b01001011 *
#408000000
0!
b1001100 #
0&
b1001100 (
#409000000
1!
b01001100 %
1&
b01001100 *
#410000000
0!
b1001101 #
0&
b1001101 (
#411000000
1!
b01001101 %
1&
b01001101 *
#412000000
0!
b1001110 #
0&
b1001110 (
#413000000
1!
b01001110 %
1&
b01001110 *
#414000000
0!
b1001111 #
0&
b1001111 (
#415000000
1!
b01001111 %
1&
b01001111 *
#416000000
0!
b1010000 #
0&
b1010000 (
#417000000
1!
b01010000 %
1&
b01010000 *
#418000000
0!
b1010001 #
0&
b1010001 (
#419000000
1!
b01010001 %
1&
b01010001 *
#420000000
0!
b1010010 #
0&
b1010010 (
#421000000
1!
b01010010 %
1&
b01010010 *
#422000000
0!
b1010011 #
0&
b1010011 (
#423000000
1!
b01010011 %
1&
b01010011 *
#424000000
0!
b1010100 #
0&
b1010100 (
#425000000
1!
b01010100 %
1&
b01010100 *
#426000000
0!
b1010101 #
0&
b1010101 (
#427000000
1!
b01010101 %
1&
b01010101 *
#428000000
0!
b1010110 #
0&
b1010110 (
#429000000
1!
b01010110 %
1&
b01010110 *
#430000000
0!
b1010111 #
0&
b1010111 (
#431000000
1!
b01010111 %
1&
b01010111 *
#432000000
0!
b1011000 #
0&
b1011000 (
#433000000
1!
b01011000 %
1&
b01011000 *
#434000000
0!
b1011001 #
0&
b1011001 (
#435000000
1!
b01011001 %
1&
b01011001 *
#436000000
0!
b1011010 #
0&
b1011010 (
#437000000
1!
b01011010 %
1&
b01011010 *
#438000000
0!
b1011011 #
0&
b1011011 (
#439000000
1!
b01011011 %
1&
b01011011 *
#440000000
0!
b1011100 #
0&
b1011100 (
#441000000
1!
b01011100 %
1&
b01011100 *
#442000000
0!
b1011101 #
0&
b1011101 (
#443000000
1!
b01011101 %
1&
b01011101 *
#444000000
0!
b1011110 #
0&
b1011110 (
#445000000
1!
b01011110 %
1&
b01011110 *
#446000000
0!
b1011111 #
0&
b1011111 (
#447000000
1!
b01011111 %
1&
b01011111 *
#448000000
0!
b1100000 #
0&
b1100000 (
#449000000
1!
b01100000 %
1&
b01100000 *
#450000000
0!
b1100001 #
0&
b1100001 (
#451000000
1!
b01100001 %
1&
b01100001 *
#452000000
0!
b1100010 #
0&
b1100010 (
#453000000
1!
b01100010 %
1&
b01100010 *
#454000000
0!
b1100011 #
0&
b1100011 (
#455000000
1!
b01100011 %
1&
b01100011 *
#456000000
0!
b1100100 #
0&
b1100100 (
#457000000
1!
b01100100 %
1&
b01100100 *
#458000000
0!
b1100101 #
0&
b1100101 (
#459000000
1!
b01100101 %
1&
b01100101 *
#460000000
0!
b1100110 #
0&
b1100110 (
#461000000
1!
b01100110 %
1&
b01100110 *
#462000000
0!
b1100111 #
0&
b1100111 (
#463000000
1!
b01100111 %
1&
b01100111 *
#464000000
0!
b1101000 #
0&
b1101000 (
#465000000
1!
b01101000 %
1&
b01101000 *
#466000000
0!
b1101001 #
0&
b1101001 (
#467000000
1!
b01101001 %
1&
b01101001 *
#468000000
0!
b1101010 #
0&
b1101010 (
#469000000
1!
b01101010 %
1&
b01101010 *
#470000000
0!
b1101011 #
0&
b1101011 (
#471000000
1!
b01101011 %
1&
b01101011 *
#472000000
0!
b1101100 #
0&
b1101100 (
#473000000
1!
b01101100 %
1&
b01101100 *
#474000000
0!
b1101101 #
0&
b1101101 (
#475000000
1!
b01101101 %
1&
b01101101 *
#476000000
0!
b1101110 #
0&
b1101110 (
#477000000
1!
b01101110 %
1&
b01101110 *
#478000000
0!
b1101111 #
0&
b1101111 (
#479000000
1!
b01101111 %
1&
b01101111 *
#480000000
0!
b1110000 #
0&
b1110000 (
#481000000
1!
b01110000 %
1&
b01110000 *
#482000000
0!
b1110001 #
0&
b1110001 (
#483000000
1!
b01110001 %
1&
b01110001 *
#484000000
0!
b1110010 #
0&
b1110010 (
#485000000
1!
b01110010 %
1&
b01110010 *
#486000000
0!
b1110011 #
0&
b1110011 (
#487000000
1!
b01110011 %
1&
b01110011 *
#488000000
0!
b1110100 #
0&
b1110100 (
#489000000
1!
b01110100 %
1&
b01110100 *
#490000000
0!
b1110101 #
0&
b1110101 (
#491000000
1!
b01110101 %
1&
b01110101 *
#492000000
0!
b1110110 #
0&
b1110110 (
#493000000
1!
b01110110 %
1&
b01110110 *
#494000000
0!
b1110111 #
0&
b1110111 (
#495000000
1!
b01110111 %
1&
b01110111 *
#496000000
0!
b1111000 #
0&
b1111000 (
#497000000
1!
b01111000 %
1&
b01111000 *
#498000000
0!
b1111001 #
0&
b1111001 (
#499000000
1!
b01111001 %
1&
b01111001 *
#500000000
0!
b1111010 #
0&
b1111010 (
#501000000
1!
b01111010 %
1&
b01111010 *
#502000000
0!
b1111011 #
0&
b1111011 (
#503000000
1!
b01111011 %
1&
b01111011 *
#504000000
0!
b1111100 #
0&
b1111100 (
#505000000
1!
b01111100 %
1&
b01111100 *
#506000000
0!
b1111101 #
0&
b1111101 (
#507000000
1!
b01111101 %
1&
b01111101 *
#508000000
0!
b1111110 #
0&
b1111110 (
#509000000
1!
b01111110 %
1&
b01111110 *
#510000000
0!
b1111111 #
0&
b1111111 (
#511000000
1!
b01111111 %
1&
b01111111 *
#512000000
b0000000 #
b0000000 (
