nikolab1213_20/vjezba6/dekadni_brojac.vhdl
library ieee;
use ieee.std_logic_1164.all;

entity dekadni_brojac is 
port(
    data_out : out std_logic_vector(3 downto 0);
    clk, rst, mode : in std_logic
);
end dekadni_brojac;

architecture dekadni_brojac_beh of dekadni_brojac is
    type dekadno_stanje is (s0, s1, s2, s3, s4, s5, s6, s7, s8, s9);
    signal proslo_stanje : dekadno_stanje := s0;
    signal sljedece_stanje : dekadno_stanje;
begin
    process(clk, rst)
    begin
        if (rising_edge(clk)) then
            if (rst = '1') then
                proslo_stanje <= S0;
            else
                proslo_stanje <= sljedece_stanje;
            end if;
        end if;
    end process;
    process(proslo_stanje, mode)
    begin
        case proslo_stanje is
            when s0 =>
                if (mode = '0') then
                    sljedece_stanje <= s1;
                elsif (mode = '1') then
                    sljedece_stanje <= s9;
                end if;
                data_out <= "0000";
            when s1 =>
                if (mode = '0') then
                    sljedece_stanje <= s2;
                elsif (mode = '1') then
                    sljedece_stanje <= s0;
                end if;
                data_out <= "0001";
            when s2 =>
                if (mode = '0') then
                    sljedece_stanje <= s3;
                elsif (mode = '1') then
                    sljedece_stanje <= s1;
                end if;
                data_out <= "0010";
            when s3 =>
                if (mode = '0') then
                    sljedece_stanje <= s4;
                elsif (mode = '1') then
                    sljedece_stanje <= s2;
                end if;
                data_out <= "0011";
            when s4 =>
                if (mode = '0') then
                    sljedece_stanje <= s5;
                elsif (mode = '1') then
                    sljedece_stanje <= s3;
                end if;
                data_out <= "0100";
            when s5 =>
                if (mode = '0') then
                    sljedece_stanje <= s6;
                elsif (mode = '1') then
                    sljedece_stanje <= s4;
                end if;
                data_out <= "0101";
            when s6 =>
                if (mode = '0') then
                    sljedece_stanje <= s7;
                elsif (mode = '1') then
                    sljedece_stanje <= s5;
                end if;
                data_out <= "0110";
            when s7 =>
                if (mode = '0') then
                    sljedece_stanje <= s8;
                elsif (mode = '1') then
                    sljedece_stanje <= s6;
                end if;
                data_out <= "0111";
            when s8 =>
                if (mode = '0') then
                    sljedece_stanje <= s9;
                elsif (mode = '1') then
                    sljedece_stanje <= s7;
                end if;
                data_out <= "1000";
            when s9 =>
                if (mode = '0') then
                    sljedece_stanje <= s0;
                elsif (mode = '1') then
                    sljedece_stanje <= s8;
                end if;
                data_out <= "1001";
        end case;
end process;
end dekadni_brojac_beh;

nikolab1213_20/vjezba6/dekadni_brojac_tb.vhdl
library ieee;
use ieee.std_logic_1164.all;

entity dekadni_brojac_testbench is
end dekadni_brojac_testbench;

architecture dekadni_brojac_tb of dekadni_brojac_testbench is
    component dekadni_brojac is
        port(
            data_out : out std_logic_vector(3 downto 0);
            clk, rst, mode : in std_logic
        );
    end component;

signal data_out1 : std_logic_vector(3 downto 0);
signal clk1, rst1, mode1 : std_logic;

begin
    DUT: dekadni_brojac port map(
        data_out => data_out1,
        mode => mode1,
        clk => clk1,
        rst => rst1
    );

    process 
    begin
    
        rst1 <= '0';
        clk1 <= '0';
        mode1 <= '0';
        wait for 1 ns;
        clk1 <= '0';
        assert(data_out1 = "0000") report "Fail data_out = 0" severity error;
        wait for 1 ns;

        rst1 <= '0';
        clk1 <= '1';
        mode1 <= '0';
        wait for 1 ns;
        clk1 <= '0';
        assert(data_out1 = "0001") report "Fail data_out = 1" severity error;
        wait for 1 ns;

        rst1 <= '0';
        clk1 <= '1';
        mode1 <= '0';
        wait for 1 ns;
        clk1 <= '0';
        assert(data_out1 = "0010") report "Fail data_out = 2" severity error;
        mode1 <= '1';
        wait for 1 ns;

        rst1 <= '0';
        clk1 <= '1';
        mode1 <= '1';
        wait for 1 ns;
        clk1 <= '0';
        assert(data_out1 = "0001") report "Fail data_out = 1" severity error;
        wait for 1 ns;

        rst1 <= '0';
        clk1 <= '1';
        mode1 <= '1';
        wait for 1 ns;
        clk1 <= '0';
        assert(data_out1 = "0000") report "Fail data_out = 0" severity error;
        wait for 1 ns;

        rst1 <= '0';
        clk1 <= '1';
        mode1 <= '1';
        wait for 1 ns;
        clk1 <= '0';
        assert(data_out1 = "1001") report "Fail data_out = 9" severity error;
        wait for 1 ns;

        rst1 <= '0';
        clk1 <= '1';
        mode1 <= '1';
        wait for 1 ns;
        clk1 <= '0';
        assert(data_out1 = "1000") report "Fail data_out = 8" severity error;
        rst1 <= '1';
        wait for 1 ns;

        rst1 <= '1';
        clk1 <= '1';
        mode1 <= '1';
        wait for 1 ns;
        clk1 <= '0';
        assert(data_out1 = "0000") report "Fail data_out = 0" severity error;
        wait for 1 ns;

        assert false report "Test finished" severity note;
        wait;

end process;
end dekadni_brojac_tb;

nikolab1213_20/vjezba6/dekadni_brojac.vcd
$date
  Fri Aug  4 14:48:44 2023
$end
$version
  GHDL v0
$end
$timescale
  1 fs
$end
$scope module standard $end
$upscope $end
$scope module std_logic_1164 $end
$upscope $end
$scope module dekadni_brojac_testbench $end
$var reg 4 ! data_out1[3:0] $end
$var reg 1 " clk1 $end
$var reg 1 # rst1 $end
$var reg 1 $ mode1 $end
$scope module dut $end
$var reg 4 % data_out[3:0] $end
$var reg 1 & clk $end
$var reg 1 ' rst $end
$var reg 1 ( mode $end
$comment proslo_stanje is not handled $end
$comment sljedece_stanje is not handled $end
$upscope $end
$upscope $end
$enddefinitions $end
#0
b0000 !
0"
0#
0$
b0000 %
0&
0'
0(
#1000000
#2000000
b0001 !
1"
b0001 %
1&
#3000000
0"
0&
#4000000
b0010 !
1"
b0010 %
1&
#5000000
0"
1$
0&
1(
#6000000
b0001 !
1"
b0001 %
1&
#7000000
0"
0&
#8000000
b0000 !
1"
b0000 %
1&
#9000000
0"
0&
#10000000
b1001 !
1"
b1001 %
1&
#11000000
0"
0&
#12000000
b1000 !
1"
b1000 %
1&
#13000000
0"
1#
0&
1'
#14000000
b0000 !
1"
b0000 %
1&
