nikolab1213_20/vjezba6/pomjeracki_registar.vhdl
library ieee;
use ieee.std_logic_1164.all;

entity pomjeracki_registar is 
port(
    data_in : in std_logic_vector(5 downto 0);
    data_out : out std_logic_vector(5 downto 0);
    mode : in std_logic_vector(1 downto 0);
    clk, clr, rin, lin : in std_logic
);
end pomjeracki_registar;

architecture pomjeracki_registar_beh of pomjeracki_registar is
    signal stanje : std_logic_vector(5 downto 0) := "000000";
    signal staro_stanje : std_logic_vector(5 downto 0) := "000000";
begin
    process(clk, clr)
    variable i : integer;
    begin 
        staro_stanje <= stanje;
        if (clr = '0') then
            stanje <= "000000";
        else
            if (rising_edge(clk)) then
                case mode is
                    when "00" =>
                        stanje <= staro_stanje;
                    when "01" =>
                        stanje(5) <= rin;
                        for i in 0 to 4 loop
                            stanje(i) <= staro_stanje(i + 1);
                        end loop;
                    when "10" =>
                        stanje(0) <= lin;
                        for i in 1 to 5 loop
                            stanje(i) <= staro_stanje(i - 1);
                        end loop;
                    when "11" => 
                        stanje <= data_in;
                    when others =>
                        stanje <= staro_stanje;
                end case;
            end if;
        end if;
    end process;
    data_out <= stanje;
end pomjeracki_registar_beh;

nikolab1213_20/vjezba6/pomjeracki_registar_tb.vhdl
library ieee;
use ieee.std_logic_1164.all;

entity pomjeracki_registar_testbench is
end pomjeracki_registar_testbench;

architecture pomjeracki_registar_tb of pomjeracki_registar_testbench is
    component pomjeracki_registar is
        port(
            data_in : in std_logic_vector(5 downto 0);
            data_out : out std_logic_vector(5 downto 0);
            mode : in std_logic_vector(1 downto 0);
            clk, clr, rin, lin : in std_logic
        );
    end component;

    signal data_in1, data_out1 : std_logic_vector(5 downto 0);
    signal mode1 : std_logic_vector(1 downto 0);
    signal clk1, clr1, rin1, lin1 : std_logic;

begin
    DUT: pomjeracki_registar port map(
        data_in => data_in1, 
        data_out => data_out1,
        mode => mode1,
        clk => clk1,
        clr => clr1,
        rin => rin1,
        lin => lin1
    );

process 
begin

    data_in1 <= "000000";
    clr1 <= '1';
    clk1 <= '0';
    mode1 <= "00";
    rin1 <= '0';
    lin1 <= '0';
    wait for 1 ns;
    clk1 <= '0';
    assert(data_out1 = "000000") report "Fail data_out = 0" severity error;
    wait for 1 ns;

    data_in1 <= "100001";
    clr1 <= '1';
    clk1 <= '1';
    mode1 <= "11";
    rin1 <= '0';
    lin1 <= '0';
    wait for 1 ns;
    clk1 <= '0';
    assert(data_out1 = "100001") report "Fail data_out = 100001" severity error;
    wait for 1 ns;

    data_in1 <= "100001";
    clr1 <= '1';
    clk1 <= '1';
    mode1 <= "01";
    rin1 <= '0';
    lin1 <= '0';
    wait for 1 ns;
    clk1 <= '0';
    assert(data_out1 = "010000") report "Fail data_out = 010000" severity error;
    wait for 1 ns;

    data_in1 <= "100001";
    clr1 <= '1';
    clk1 <= '1';
    mode1 <= "01";
    rin1 <= '1';
    lin1 <= '0';
    wait for 1 ns;
    clk1 <= '0';
    assert(data_out1 = "101000") report "Fail data_out = 101000" severity error;
    wait for 1 ns;

    data_in1 <= "100001";
    clr1 <= '1';
    clk1 <= '1';
    mode1 <= "10";
    rin1 <= '0';
    lin1 <= '0';
    wait for 1 ns;
    clk1 <= '0';
    assert(data_out1 = "010000") report "Fail data_out = 010000" severity error;
    wait for 1 ns;

    data_in1 <= "100001";
    clr1 <= '1';
    clk1 <= '1';
    mode1 <= "10";
    rin1 <= '0';
    lin1 <= '1';
    wait for 1 ns;
    clk1 <= '0';
    assert(data_out1 = "100001") report "Fail data_out = 100001" severity error;
    wait for 1 ns;

    data_in1 <= "100001";
    clr1 <= '0';
    clk1 <= '1';
    mode1 <= "10";
    rin1 <= '0';
    lin1 <= '1';
    wait for 1 ns;
    clk1 <= '0';
    assert(data_out1 = "000000") report "Fail data_out = 000000" severity error;
    wait for 1 ns;

    assert false report "Test finished" severity note;
    wait;

end process;
end pomjeracki_registar_tb;

nikolab1213_20/vjezba6/pomjeracki_registar.vcd
$date
  Thu Aug  3 13:36:44 2023
$end
$version
  GHDL v0
$end
$timescale
  1 fs
$end
$scope module standard $end
$upscope $end
$scope module std_logic_1164 $end
$upscope $end
$scope module pomjeracki_registar_testbench $end
$var reg 6 ! data_in1[5:0] $end
$var reg 6 " data_out1[5:0] $end
$var reg 2 # mode1[1:0] $end
$var reg 1 $ clk1 $end
$var reg 1 % clr1 $end
$var reg 1 & rin1 $end
$var reg 1 ' lin1 $end
$scope module dut $end
$var reg 6 ( data_in[5:0] $end
$var reg 6 ) data_out[5:0] $end
$var reg 2 * mode[1:0] $end
$var reg 1 + clk $end
$var reg 1 , clr $end
$var reg 1 - rin $end
$var reg 1 . lin $end
$var reg 6 / stanje[5:0] $end
$var reg 6 0 staro_stanje[5:0] $end
$upscope $end
$upscope $end
$enddefinitions $end
#0
b000000 !
b000000 "
b00 #
0$
1%
0&
0'
b000000 (
b000000 )
b00 *
0+
1,
0-
0.
b000000 /
b000000 0
#1000000
#2000000
b100001 !
b100001 "
b11 #
1$
b100001 (
b100001 )
b11 *
1+
b100001 /
#3000000
0$
0+
b100001 0
#4000000
b010000 "
b01 #
1$
b010000 )
b01 *
1+
b010000 /
#5000000
0$
0+
b010000 0
#6000000
b101000 "
1$
1&
b101000 )
1+
1-
b101000 /
#7000000
0$
0+
b101000 0
#8000000
b010000 "
b10 #
1$
0&
b010000 )
b10 *
1+
0-
b010000 /
#9000000
0$
0+
b010000 0
#10000000
b100001 "
1$
1'
b100001 )
1+
1.
b100001 /
#11000000
0$
0+
b100001 0
#12000000
b000000 "
1$
0%
b000000 )
1+
0,
b000000 /
#13000000
0$
0+
b000000 0
