nikolab1213_20/vjezba6/stacionarni_registar.vhdl
library ieee;
use ieee.std_logic_1164.all;

entity stacionarni_registar is
port(
    data_in : in std_logic_vector(9 downto 0);
    data_out : out std_logic_vector(9 downto 0);
    enable, clk, clr : in std_logic
);
end stacionarni_registar;

architecture stacionarni_registar_beh of stacionarni_registar is
signal stanje : std_logic_vector(9 downto 0) := "0000000000";
begin
    process(clk, clr)
    begin
        if (clk = '1' and clk'event) then
            if (clr = '1') then
                stanje <= "0000000000";
            elsif (enable = '1') then
                stanje <= data_in;
            end if;
        end if;
    data_out <= stanje;
    end process;
end stacionarni_registar_beh;

nikolab1213_20/vjezba6/stacionarni_registar_tb.vhdl
library ieee;
use ieee.std_logic_1164.all;

entity stacionarni_registar_testbench is
end stacionarni_registar_testbench;

architecture stacionarni_registar_tb of stacionarni_registar_testbench is
    component stacionarni_registar is
        port(
            data_in : in std_logic_vector(9 downto 0);
            data_out : out std_logic_vector(9 downto 0);
            enable, clk, clr : in std_logic
        );
    end component;

    signal data_in1, data_out1 : std_logic_vector(9 downto 0);
    signal enable1, clk1, clr1 : std_logic;

begin
    DUT: stacionarni_registar port map(
        data_in => data_in1, 
        data_out => data_out1,
        enable => enable1,
        clk => clk1,
        clr => clr1
    );

process 
begin

    data_in1 <= "0000000000";
    enable1 <= '0';
    clr1 <= '0';
    clk1 <= '0';
    wait for 1 ns;
    clk1 <= '0';
    assert(data_out1 = "0000000000") report "Fail data_out = 0" severity error;
    wait for 1 ns;

    data_in1 <= "0000000001";
    enable1 <= '1';
    clr1 <= '0';
    clk1 <= '1';
    wait for 1 ns;
    clk1 <= '0';
    wait for 1 ns;
    assert(data_out1 = "0000000001") report "Fail data_out = 1" severity error;
    wait for 1 ns;

    data_in1 <= "1000000000";
    enable1 <= '1';
    clr1 <= '1';
    clk1 <= '1';
    wait for 1 ns;
    clk1 <= '0';
    wait for 1 ns;
    assert(data_out1 = "0000000000") report "Fail data_out = 0" severity error;
    wait for 1 ns;

    data_in1 <= "1000000001";
    enable1 <= '1';
    clr1 <= '0';
    clk1 <= '1';
    wait for 1 ns;
    clk1 <= '0';
    wait for 1 ns;
    assert(data_out1 = "1000000001") report "Fail data_out = 513" severity error;
    wait for 1 ns;

    data_in1 <= "1111111111";
    enable1 <= '0';
    clr1 <= '0';
    clk1 <= '1';
    wait for 1 ns;
    clk1 <= '0';
    wait for 1 ns;
    assert(data_out1 = "1000000001") report "Fail data_out = 513" severity error;
    wait for 1 ns;

    data_in1 <= "1111111111";
    enable1 <= '0';
    clr1 <= '1';
    clk1 <= '1';
    wait for 1 ns;
    clk1 <= '0';
    wait for 1 ns;
    assert(data_out1 = "0000000000") report "Fail data_out = 0" severity error;
    wait for 1 ns;

    assert false report "Test finished" severity note;
    wait;

end process;
end stacionarni_registar_tb;

nikolab1213_20/vjezba6/stacionarni_registar.vcd
$date
  Thu Aug  3 12:53:25 2023
$end
$version
  GHDL v0
$end
$timescale
  1 fs
$end
$scope module standard $end
$upscope $end
$scope module std_logic_1164 $end
$upscope $end
$scope module stacionarni_registar_testbench $end
$var reg 10 ! data_in1[9:0] $end
$var reg 10 " data_out1[9:0] $end
$var reg 1 # enable1 $end
$var reg 1 $ clk1 $end
$var reg 1 % clr1 $end
$scope module dut $end
$var reg 10 & data_in[9:0] $end
$var reg 10 ' data_out[9:0] $end
$var reg 1 ( enable $end
$var reg 1 ) clk $end
$var reg 1 * clr $end
$var reg 10 + stanje[9:0] $end
$upscope $end
$upscope $end
$enddefinitions $end
#0
b0000000000 !
b0000000000 "
0#
0$
0%
b0000000000 &
b0000000000 '
0(
0)
0*
b0000000000 +
#1000000
#2000000
b0000000001 !
1#
1$
b0000000001 &
1(
1)
b0000000001 +
#3000000
b0000000001 "
0$
b0000000001 '
0)
#4000000
#5000000
b1000000000 !
1$
1%
b1000000000 &
1)
1*
b0000000000 +
#6000000
b0000000000 "
0$
b0000000000 '
0)
#7000000
#8000000
b1000000001 !
1$
0%
b1000000001 &
1)
0*
b1000000001 +
#9000000
b1000000001 "
0$
b1000000001 '
0)
#10000000
#11000000
b1111111111 !
0#
1$
b1111111111 &
0(
1)
#12000000
0$
0)
#13000000
#14000000
1$
1%
1)
1*
b0000000000 +
#15000000
b0000000000 "
0$
b0000000000 '
0)
